Workbook

Sheet Raw Data
A1: Manufacturer | B1: Model | C1: Sales_in_thousands | D1: __year_resale_value | E1: Vehicle_type | F1: Price_in_thousands | G1: Engine_size | H1: Horsepower | I1: Wheelbase | J1: Width | K1: Length | L1: Curb_weight | M1: Fuel_capacity | N1: Fuel_efficiency | O1: Latest_Launch | P1: Power_perf_factor
A2: Acura | B2: Integra | C2: 16.919 | D2: 16.36 | E2: Passenger | F2: 21.5 | G2: 1.8 | H2: 140 | I2: 101.2 | J2: 67.3 | K2: 172.4 | L2: 2.639 | M2: 13.2 | N2: 28 | O2: 2/2/2012 | P2: 58.28015
A3: Acura | B3: TL | C3: 39.384 | D3: 19.875 | E3: Passenger | F3: 28.4 | G3: 3.2 | H3: 225 | I3: 108.1 | J3: 70.3 | K3: 192.9 | L3: 3.517 | M3: 17.2 | N3: 25 | O3: 6/3/2011 | P3: 91.370778
A4: Acura | B4: CL | C4: 14.114 | D4: 18.225 | E4: Passenger | G4: 3.2 | H4: 225 | I4: 106.9 | J4: 70.6 | K4: 192 | L4: 3.47 | M4: 17.2 | N4: 26 | O4: 1/4/2012
A5: Acura | B5: RL | C5: 8.588 | D5: 29.725 | E5: Passenger | F5: 42 | G5: 3.5 | H5: 210 | I5: 114.6 | J5: 71.4 | K5: 196.6 | L5: 3.85 | M5: 18 | N5: 22 | O5: 3/10/2011 | P5: 91.389779
A6: Audi | B6: A4 | C6: 20.397 | D6: 22.255 | E6: Passenger | F6: 23.99 | G6: 1.8 | H6: 150 | I6: 102.6 | J6: 68.2 | K6: 178 | L6: 2.998 | M6: 16.4 | N6: 27 | O6: 10/8/2011 | P6: 62.777639
A7: Audi | B7: A6 | C7: 18.78 | D7: 23.555 | E7: Passenger | F7: 33.95 | G7: 2.8 | H7: 200 | I7: 108.7 | J7: 76.1 | K7: 192 | L7: 3.561 | M7: 18.5 | N7: 22 | O7: 8/9/2011 | P7: 84.565105
A8: Audi | B8: A8 | C8: 1.38 | D8: 39 | E8: Passenger | F8: 62 | G8: 4.2 | H8: 310 | I8: 113 | J8: 74 | K8: 198.2 | L8: 3.902 | M8: 23.7 | N8: 21 | O8: 2/27/2012 | P8: 134.65686
A9: BMW | B9: 323i | C9: 19.747 | E9: Passenger | F9: 26.99 | G9: 2.5 | H9: 170 | I9: 107.3 | J9: 68.4 | K9: 176 | L9: 3.179 | M9: 16.6 | N9: 26 | O9: 6/28/2011 | P9: 71.191207
A10: BMW | B10: 328i | C10: 9.231 | D10: 28.675 | E10: Passenger | F10: 33.4 | G10: 2.8 | H10: 193 | I10: 107.3 | J10: 68.5 | K10: 176 | L10: 3.197 | M10: 16.6 | N10: 24 | O10: 1/29/2012 | P10: 81.877069
A11: BMW | B11: 528i | C11: 17.527 | D11: 36.125 | E11: Passenger | F11: 38.9 | G11: 2.8 | H11: 193 | I11: 111.4 | J11: 70.9 | K11: 188 | L11: 3.472 | M11: 18.5 | N11: 25 | O11: 4/4/2011 | P11: 83.998724
A12: Buick | B12: Century | C12: 91.561 | D12: 12.475 | E12: Passenger | F12: 21.975 | G12: 3.1 | H12: 175 | I12: 109 | J12: 72.7 | K12: 194.6 | L12: 3.368 | M12: 17.5 | N12: 25 | O12: 11/2/2011 | P12: 71.181451
A13: Buick | B13: Regal | C13: 39.35 | D13: 13.74 | E13: Passenger | F13: 25.3 | G13: 3.8 | H13: 240 | I13: 109 | J13: 72.7 | K13: 196.2 | L13: 3.543 | M13: 17.5 | N13: 23 | O13: 9/3/2011 | P13: 95.636703
A14: Buick | B14: Park Avenue | C14: 27.851 | D14: 20.19 | E14: Passenger | F14: 31.965 | G14: 3.8 | H14: 205 | I14: 113.8 | J14: 74.7 | K14: 206.8 | L14: 3.778 | M14: 18.5 | N14: 24 | O14: 3/23/2012 | P14: 85.828408
A15: Buick | B15: LeSabre | C15: 83.257 | D15: 13.36 | E15: Passenger | F15: 27.885 | G15: 3.8 | H15: 205 | I15: 112.2 | J15: 73.5 | K15: 200 | L15: 3.591 | M15: 17.5 | N15: 25 | O15: 7/23/2011 | P15: 84.254526
A16: Cadillac | B16: DeVille | C16: 63.729 | D16: 22.525 | E16: Passenger | F16: 39.895 | G16: 4.6 | H16: 275 | I16: 115.3 | J16: 74.5 | K16: 207.2 | L16: 3.978 | M16: 18.5 | N16: 22 | O16: 2/23/2012 | P16: 113.8546
A17: Cadillac | B17: Seville | C17: 15.943 | D17: 27.1 | E17: Passenger | F17: 44.475 | G17: 4.6 | H17: 275 | I17: 112.2 | J17: 75 | K17: 201 | M17: 18.5 | N17: 22 | O17: 4/29/2011 | P17: 115.62136
A18: Cadillac | B18: Eldorado | C18: 6.536 | D18: 25.725 | E18: Passenger | F18: 39.665 | G18: 4.6 | H18: 275 | I18: 108 | J18: 75.5 | K18: 200.6 | L18: 3.843 | M18: 19 | N18: 22 | O18: 11/27/2011 | P18: 113.76587
A19: Cadillac | B19: Catera | C19: 11.185 | D19: 18.225 | E19: Passenger | F19: 31.01 | G19: 3 | H19: 200 | I19: 107.4 | J19: 70.3 | K19: 194.8 | L19: 3.77 | M19: 18 | N19: 22 | O19: 9/28/2011 | P19: 83.483094
A20: Cadillac | B20: Escalade | C20: 14.785 | E20: Car | F20: 46.225 | G20: 5.7 | H20: 255 | I20: 117.5 | J20: 77 | K20: 201.2 | L20: 5.572 | M20: 30 | N20: 15 | O20: 4/17/2012 | P20: 109.50912
A21: Chevrolet | B21: Cavalier | C21: 145.519 | D21: 9.25 | E21: Passenger | F21: 13.26 | G21: 2.2 | H21: 115 | I21: 104.1 | J21: 67.9 | K21: 180.9 | L21: 2.676 | M21: 14.3 | N21: 27 | O21: 8/17/2011 | P21: 46.363347
A22: Chevrolet | B22: Malibu | C22: 135.126 | D22: 11.225 | E22: Passenger | F22: 16.535 | G22: 3.1 | H22: 170 | I22: 107 | J22: 69.4 | K22: 190.4 | L22: 3.051 | M22: 15 | N22: 25 | O22: 3/19/2012 | P22: 67.314462
A23: Chevrolet | B23: Lumina | C23: 24.629 | D23: 10.31 | E23: Passenger | F23: 18.89 | G23: 3.1 | H23: 175 | I23: 107.5 | J23: 72.5 | K23: 200.9 | L23: 3.33 | M23: 16.6 | N23: 25 | O23: 5/24/2011 | P23: 69.991396
A24: Chevrolet | B24: Monte Carlo | C24: 42.593 | D24: 11.525 | E24: Passenger | F24: 19.39 | G24: 3.4 | H24: 180 | I24: 110.5 | J24: 72.7 | K24: 197.9 | L24: 3.34 | M24: 17 | N24: 27 | O24: 12/22/2011 | P24: 72.030917
A25: Chevrolet | B25: Camaro | C25: 26.402 | D25: 13.025 | E25: Passenger | F25: 24.34 | G25: 3.8 | H25: 200 | I25: 101.1 | J25: 74.1 | K25: 193.2 | L25: 3.5 | M25: 16.8 | N25: 25 | O25: 10/23/2011 | P25: 81.118543
A26: Chevrolet | B26: Corvette | C26: 17.947 | D26: 36.225 | E26: Passenger | F26: 45.705 | G26: 5.7 | H26: 345 | I26: 104.5 | J26: 73.6 | K26: 179.7 | L26: 3.21 | M26: 19.1 | N26: 22 | O26: 5/12/2012 | P26: 141.14115
A27: Chevrolet | B27: Prizm | C27: 32.299 | D27: 9.125 | E27: Passenger | F27: 13.96 | G27: 1.8 | H27: 120 | I27: 97.1 | J27: 66.7 | K27: 174.3 | L27: 2.398 | M27: 13.2 | N27: 33 | O27: 9/11/2011 | P27: 48.297636
A28: Chevrolet | B28: Metro | C28: 21.855 | D28: 5.16 | E28: Passenger | F28: 9.235 | G28: 1 | H28: 55 | I28: 93.1 | J28: 62.6 | K28: 149.4 | L28: 1.895 | M28: 10.3 | N28: 45 | O28: 4/13/2012 | P28: 23.276272
A29: Chevrolet | B29: Impala | C29: 107.995 | E29: Passenger | F29: 18.89 | G29: 3.4 | H29: 180 | I29: 110.5 | J29: 73 | K29: 200 | L29: 3.389 | M29: 17 | N29: 27 | O29: 6/18/2011 | P29: 71.838039
A30: Chrysler | B30: Sebring Coupe | C30: 7.854 | D30: 12.36 | E30: Passenger | F30: 19.84 | G30: 2.5 | H30: 163 | I30: 103.7 | J30: 69.7 | K30: 190.9 | L30: 2.967 | M30: 15.9 | N30: 24 | O30: 1/16/2012 | P30: 65.957184
A31: Chrysler | B31: Sebring Conv. | C31: 32.775 | D31: 14.18 | E31: Passenger | F31: 24.495 | G31: 2.5 | H31: 168 | I31: 106 | J31: 69.2 | K31: 193 | L31: 3.332 | M31: 16 | N31: 24 | O31: 11/17/2011 | P31: 69.521355
A32: Chrysler | B32: Concorde | C32: 31.148 | D32: 13.725 | E32: Passenger | F32: 22.245 | G32: 2.7 | H32: 200 | I32: 113 | J32: 74.4 | K32: 209.1 | L32: 3.452 | M32: 17 | N32: 26 | O32: 6/6/2012 | P32: 80.023782
A33: Chrysler | B33: Cirrus | C33: 32.306 | D33: 12.64 | E33: Passenger | F33: 16.48 | G33: 2 | H33: 132 | I33: 108 | J33: 71 | K33: 186 | L33: 2.911 | M33: 16 | N33: 27 | O33: 10/6/2011 | P33: 53.5662
A34: Chrysler | B34: LHS | C34: 13.462 | D34: 17.325 | E34: Passenger | F34: 28.34 | G34: 3.5 | H34: 253 | I34: 113 | J34: 74.4 | K34: 207.7 | L34: 3.564 | M34: 17 | N34: 23 | O34: 5/8/2012 | P34: 101.32928
A35: Chrysler | B35: Town & Country | C35: 53.48 | D35: 19.54 | E35: Car | O35: 7/13/2011
A36: Chrysler | B36: 300M | C36: 30.696 | E36: Passenger | F36: 29.185 | G36: 3.5 | H36: 253 | I36: 113 | J36: 74.4 | K36: 197.8 | L36: 3.567 | M36: 17 | N36: 23 | O36: 2/10/2012 | P36: 101.65524
A37: Dodge | B37: Neon | C37: 76.034 | D37: 7.75 | E37: Passenger | F37: 12.64 | G37: 2 | H37: 132 | I37: 105 | J37: 74.4 | K37: 174.4 | L37: 2.567 | M37: 12.5 | N37: 29 | O37: 12/12/2011 | P37: 52.084899
A38: Dodge | B38: Avenger | C38: 4.734 | D38: 12.545 | E38: Passenger | F38: 19.045 | G38: 2.5 | H38: 163 | I38: 103.7 | J38: 69.1 | K38: 190.2 | L38: 2.879 | M38: 15.9 | N38: 24 | O38: 7/1/2012 | P38: 65.650508
A39: Dodge | B39: Stratus | C39: 71.186 | D39: 10.185 | E39: Passenger | F39: 20.23 | G39: 2.5 | H39: 168 | I39: 108 | J39: 71 | K39: 186 | L39: 3.058 | M39: 16 | N39: 24 | O39: 10/31/2011 | P39: 67.876108
A40: Dodge | B40: Intrepid | C40: 88.028 | D40: 12.275 | E40: Passenger | F40: 22.505 | G40: 2.7 | H40: 202 | I40: 113 | J40: 74.7 | K40: 203.7 | L40: 3.489 | M40: 17 | O40: 6/2/2012 | P40: 80.83147
A41: Dodge | B41: Viper | C41: 0.916 | D41: 58.47 | E41: Passenger | F41: 69.725 | G41: 8 | H41: 450 | I41: 96.2 | J41: 75.7 | K41: 176.7 | L41: 3.375 | M41: 19 | N41: 16 | O41: 8/7/2011 | P41: 188.14432
A42: Dodge | B42: Ram Pickup | C42: 227.061 | D42: 15.06 | E42: Car | F42: 19.46 | G42: 5.2 | H42: 230 | I42: 138.7 | J42: 79.3 | K42: 224.2 | L42: 4.47 | M42: 26 | N42: 17 | O42: 3/6/2012 | P42: 90.2117
A43: Dodge | B43: Ram Wagon | C43: 16.767 | D43: 15.51 | E43: Car | F43: 21.315 | G43: 3.9 | H43: 175 | I43: 109.6 | J43: 78.8 | K43: 192.6 | L43: 4.245 | M43: 32 | N43: 15 | O43: 1/6/2012 | P43: 71.135292
A44: Dodge | B44: Ram Van | C44: 31.038 | D44: 13.425 | E44: Car | F44: 18.575 | G44: 3.9 | H44: 175 | I44: 127.2 | J44: 78.8 | K44: 208.5 | L44: 4.298 | M44: 32 | N44: 16 | O44: 7/26/2012 | P44: 70.078322
A45: Dodge | B45: Dakota | C45: 111.313 | D45: 11.26 | E45: Car | F45: 16.98 | G45: 2.5 | H45: 120 | I45: 131 | J45: 71.5 | K45: 215 | L45: 3.557 | M45: 22 | N45: 19 | O45: 11/25/2011 | P45: 49.645002
A46: Dodge | B46: Durango | C46: 101.323 | E46: Car | F46: 26.31 | G46: 5.2 | H46: 230 | I46: 115.7 | J46: 71.7 | K46: 193.5 | L46: 4.394 | M46: 25 | N46: 17 | O46: 6/27/2012 | P46: 92.854125
A47: Dodge | B47: Caravan | C47: 181.749 | D47: 12.025 | E47: Car | F47: 19.565 | G47: 2.4 | H47: 150 | I47: 113.3 | J47: 76.8 | K47: 186.3 | L47: 3.533 | M47: 20 | N47: 24 | O47: 9/1/2011 | P47: 61.227
A48: Ford | B48: Escort | C48: 70.227 | D48: 7.425 | E48: Passenger | F48: 12.07 | G48: 2 | H48: 110 | I48: 98.4 | J48: 67 | K48: 174.7 | L48: 2.468 | M48: 12.7 | N48: 30 | O48: 3/31/2012 | P48: 44.083709
A49: Ford | B49: Mustang | C49: 113.369 | D49: 12.76 | E49: Passenger | F49: 21.56 | G49: 3.8 | H49: 190 | I49: 101.3 | J49: 73.1 | K49: 183.2 | L49: 3.203 | M49: 15.7 | N49: 24 | O49: 1/31/2012 | P49: 76.509185
A50: Ford | B50: Contour | C50: 35.068 | D50: 8.835 | E50: Passenger | F50: 17.035 | G50: 2.5 | H50: 170 | I50: 106.5 | J50: 69.1 | K50: 184.6 | L50: 2.769 | M50: 15 | N50: 25 | O50: 8/20/2012 | P50: 67.351011
A51: Ford | B51: Taurus | C51: 245.815 | D51: 10.055 | E51: Passenger | F51: 17.885 | G51: 3 | H51: 155 | I51: 108.5 | J51: 73 | K51: 197.6 | L51: 3.368 | M51: 16 | N51: 24 | O51: 12/20/2011 | P51: 62.50374
A52: Ford | B52: Focus | C52: 175.67 | E52: Passenger | F52: 12.315 | G52: 2 | H52: 107 | I52: 103 | J52: 66.9 | K52: 174.8 | L52: 2.564 | M52: 13.2 | N52: 30 | O52: 7/22/2012 | P52: 43.117132
A53: Ford | B53: Crown Victoria | C53: 63.403 | D53: 14.21 | E53: Passenger | F53: 22.195 | G53: 4.6 | H53: 200 | I53: 114.7 | J53: 78.2 | K53: 212 | L53: 3.908 | M53: 19 | N53: 21 | O53: 9/26/2011 | P53: 80.499537
A54: Ford | B54: Explorer | C54: 276.747 | D54: 16.64 | E54: Car | F54: 31.93 | G54: 4 | H54: 210 | I54: 111.6 | J54: 70.2 | K54: 190.7 | L54: 3.876 | M54: 21 | N54: 19 | O54: 4/25/2012 | P54: 87.635496
A55: Ford | B55: Windstar | C55: 155.787 | D55: 13.175 | E55: Car | F55: 21.41 | G55: 3 | H55: 150 | I55: 120.7 | J55: 76.6 | K55: 200.9 | L55: 3.761 | M55: 26 | N55: 21 | O55: 2/25/2012 | P55: 62.095048
A56: Ford | B56: Expedition | C56: 125.338 | D56: 23.575 | E56: Car | F56: 36.135 | G56: 4.6 | H56: 240 | I56: 119 | J56: 78.7 | K56: 204.6 | L56: 4.808 | M56: 26 | N56: 16 | O56: 9/14/2012 | P56: 100.0248
A57: Ford | B57: Ranger | C57: 220.65 | D57: 7.85 | E57: Car | F57: 12.05 | G57: 2.5 | H57: 119 | I57: 117.5 | J57: 69.4 | K57: 200.7 | L57: 3.086 | M57: 20 | N57: 23 | O57: 1/14/2012 | P57: 47.389531
A58: Ford | B58: F-Series | C58: 540.561 | D58: 15.075 | E58: Car | F58: 26.935 | G58: 4.6 | H58: 220 | I58: 138.5 | J58: 79.1 | K58: 224.5 | L58: 4.241 | M58: 25.1 | N58: 18 | O58: 8/16/2012 | P58: 89.401935
A59: Honda | B59: Civic | C59: 199.685 | D59: 9.85 | E59: Passenger | F59: 12.885 | G59: 1.6 | H59: 106 | I59: 103.2 | J59: 67.1 | K59: 175.1 | L59: 2.339 | M59: 11.9 | N59: 32 | O59: 10/21/2011 | P59: 42.879097
A60: Honda | B60: Accord | C60: 230.902 | D60: 13.21 | E60: Passenger | F60: 15.35 | G60: 2.3 | H60: 135 | I60: 106.9 | J60: 70.3 | K60: 188.8 | L60: 2.932 | M60: 17.1 | N60: 27 | O60: 5/20/2012 | P60: 54.269548
A61: Honda | B61: CR-V | C61: 73.203 | D61: 17.71 | E61: Car | F61: 20.55 | G61: 2 | H61: 146 | I61: 103.2 | J61: 68.9 | K61: 177.6 | L61: 3.219 | M61: 15.3 | N61: 24 | O61: 3/21/2012 | P61: 60.087967
A62: Honda | B62: Passport | C62: 12.855 | D62: 17.525 | E62: Car | F62: 26.6 | G62: 3.2 | H62: 205 | I62: 106.4 | J62: 70.4 | K62: 178.2 | L62: 3.857 | M62: 21.1 | N62: 19 | O62: 10/9/2012 | P62: 83.602501
A63: Honda | B63: Odyssey | C63: 76.029 | D63: 19.49 | E63: Car | F63: 26 | G63: 3.5 | H63: 210 | I63: 118.1 | J63: 75.6 | K63: 201.2 | L63: 4.288 | M63: 20 | N63: 23 | O63: 2/8/2012 | P63: 85.217691
A64: Hyundai | B64: Accent | C64: 41.184 | D64: 5.86 | E64: Passenger | F64: 9.699 | G64: 1.5 | H64: 92 | I64: 96.1 | J64: 65.7 | K64: 166.7 | L64: 2.24 | M64: 11.9 | N64: 31 | O64: 9/10/2012 | P64: 36.672284
... A67: Infiniti | B67: I30 | C67: 23.713 | D67: 19.69 | E67: Passenger | F67: 29.465 | G67: 3 | H67: 227 | I67: 108.3 | J67: 70.2 | K67: 193.7 | L67: 3.342 | M67: 18.5 | N67: 25 | O67: 4/15/2012 | P67: 92.436889
A68: Jaguar | B68: S-Type | C68: 15.467 | E68: Passenger | F68: 42.8 | G68: 3 | H68: 240 | I68: 114.5 | J68: 71.6 | K68: 191.3 | L68: 3.65 | M68: 18.4 | N68: 21 | O68: 11/3/2012 | P68: 102.17898
A69: Jeep | B69: Wrangler | C69: 55.557 | D69: 13.475 | E69: Car | F69: 14.46 | G69: 2.5 | H69: 120 | I69: 93.4 | J69: 66.7 | K69: 152 | L69: 3.045 | M69: 19 | N69: 17 | O69: 3/4/2012 | P69: 48.672898
A70: Jeep | B70: Cherokee | C70: 80.556 | D70: 13.775 | E70: Car | F70: 21.62 | G70: 4 | H70: 190 | I70: 101.4 | J70: 69.4 | K70: 167.5 | L70: 3.194 | M70: 20 | N70: 20 | O70: 10/5/2012 | P70: 76.58444
A71: Jeep | B71: Grand Cherokee | C71: 157.04 | D71: 18.81 | E71: Car | F71: 26.895 | G71: 4 | H71: 195 | I71: 105.9 | J71: 72.3 | K71: 181.5 | L71: 3.88 | M71: 20.5 | N71: 19 | O71: 12/10/2011 | P71: 80.387779
A72: Lexus | B72: ES300 | C72: 24.072 | D72: 26.975 | E72: Passenger | F72: 31.505 | G72: 3 | H72: 210 | I72: 105.1 | J72: 70.5 | K72: 190.2 | L72: 3.373 | M72: 18.5 | N72: 23 | O72: 7/9/2012 | P72: 87.211001
A73: Lexus | B73: GS300 | C73: 12.698 | D73: 32.075 | E73: Passenger | F73: 37.805 | G73: 3 | H73: 225 | I73: 110.2 | J73: 70.9 | K73: 189.2 | L73: 3.638 | M73: 19.8 | N73: 23 | O73: 5/10/2012 | P73: 94.946698
A74: Lexus | B74: GS400 | C74: 3.334 | E74: Passenger | F74: 46.305 | G74: 4 | H74: 300 | I74: 110.2 | J74: 70.9 | K74: 189.2 | L74: 3.693 | M74: 19.8 | N74: 21 | O74: 11/28/2012 | P74: 125.01336
A75: Lexus | B75: LS400 | C75: 6.375 | D75: 40.375 | E75: Passenger | F75: 54.005 | G75: 4 | H75: 290 | I75: 112.2 | J75: 72 | K75: 196.7 | L75: 3.89 | M75: 22.5 | N75: 22 | O75: 3/29/2012 | P75: 124.44672
A76: Lexus | B76: LX470 | C76: 9.126 | E76: Car | F76: 60.105 | G76: 4.7 | H76: 230 | I76: 112.2 | J76: 76.4 | K76: 192.5 | L76: 5.401 | M76: 25.4 | N76: 15 | O76: 10/30/2012 | P76: 105.76046
A77: Lexus | B77: RX300 | C77: 51.238 | E77: Car | F77: 34.605 | G77: 3 | H77: 220 | I77: 103 | J77: 71.5 | K77: 180.1 | L77: 3.9 | M77: 17.2 | N77: 21 | O77: 1/4/2012 | P77: 91.943802
A78: Lincoln | B78: Continental | C78: 13.798 | D78: 20.525 | E78: Passenger | F78: 39.08 | G78: 4.6 | H78: 275 | I78: 109 | J78: 73.6 | K78: 208.5 | L78: 3.868 | M78: 20 | N78: 22 | O78: 8/3/2012 | P78: 113.54021
A79: Lincoln | B79: Town car | C79: 48.911 | D79: 21.725 | E79: Passenger | F79: 43.33 | G79: 4.6 | H79: 215 | I79: 117.7 | J79: 78.2 | K79: 215.3 | L79: 4.121 | M79: 19 | N79: 21 | O79: 6/4/2012 | P79: 93.957917
A80: Lincoln | B80: Navigator | C80: 22.925 | E80: Car | F80: 42.66 | G80: 5.4 | H80: 300 | I80: 119 | J80: 79.9 | K80: 204.8 | L80: 5.393 | M80: 30 | N80: 15 | O80: 12/23/2012 | P80: 123.97205
A81: Mitsubishi | B81: Mirage | C81: 26.232 | D81: 8.325 | E81: Passenger | F81: 13.987 | G81: 1.8 | H81: 113 | I81: 98.4 | J81: 66.5 | K81: 173.6 | L81: 2.25 | M81: 13.2 | N81: 30 | O81: 4/23/2012 | P81: 45.832181
A82: Mitsubishi | B82: Eclipse | C82: 42.541 | D82: 10.395 | E82: Passenger | F82: 19.047 | G82: 2.4 | H82: 154 | I82: 100.8 | J82: 68.9 | K82: 175.4 | L82: 2.91 | M82: 15.9 | N82: 24 | O82: 11/24/2012 | P82: 62.441962
A83: Mitsubishi | B83: Galant | C83: 55.616 | D83: 10.595 | E83: Passenger | F83: 17.357 | G83: 2.4 | H83: 145 | I83: 103.7 | J83: 68.5 | K83: 187.8 | L83: 2.945 | M83: 16.3 | N83: 25 | O83: 1/29/2012 | P83: 58.606773
A84: Mitsubishi | B84: Diamante | C84: 5.711 | D84: 16.575 | E84: Passenger | F84: 24.997 | G84: 3.5 | H84: 210 | I84: 107.1 | J84: 70.3 | K84: 194.1 | L84: 3.443 | M84: 19 | N84: 22 | O84: 8/28/2012 | P84: 84.830779
A85: Mitsubishi | B85: 3000GT | C85: 0.11 | D85: 20.94 | E85: Passenger | F85: 25.45 | G85: 3 | H85: 161 | I85: 97.2 | J85: 72.4 | K85: 180.3 | L85: 3.131 | M85: 19.8 | N85: 21 | O85: 6/29/2012 | P85: 67.544155
A86: Mitsubishi | B86: Montero | C86: 11.337 | D86: 19.125 | E86: Car | F86: 31.807 | G86: 3.5 | H86: 200 | I86: 107.3 | J86: 69.9 | K86: 186.6 | L86: 4.52 | M86: 24.3 | N86: 18 | O86: 1/17/2012 | P86: 83.920815
A87: Mitsubishi | B87: Montero Sport | C87: 39.348 | D87: 13.88 | E87: Car | F87: 22.527 | G87: 3 | H87: 173 | I87: 107.3 | J87: 66.7 | K87: 178.3 | L87: 3.51 | M87: 19.5 | N87: 20 | O87: 5/18/2012 | P87: 70.660942
A88: Mercury | B88: Mystique | C88: 14.351 | D88: 8.8 | E88: Passenger | F88: 16.24 | G88: 2 | H88: 125 | I88: 106.5 | J88: 69.1 | K88: 184.8 | L88: 2.769 | M88: 15 | N88: 28 | O88: 12/19/2012 | P88: 50.997748
A89: Mercury | B89: Cougar | C89: 26.529 | D89: 13.89 | E89: Passenger | F89: 16.54 | G89: 2 | H89: 125 | I89: 106.4 | J89: 69.6 | K89: 185 | L89: 2.892 | M89: 16 | N89: 30 | O89: 2/23/2012 | P89: 51.113474
A90: Mercury | B90: Sable | C90: 67.956 | D90: 11.03 | E90: Passenger | F90: 19.035 | G90: 3 | H90: 153 | I90: 108.5 | J90: 73 | K90: 199.7 | L90: 3.379 | M90: 16 | N90: 24 | O90: 9/22/2012 | P90: 62.239967
A91: Mercury | B91: Grand Marquis | C91: 81.174 | D91: 14.875 | E91: Passenger | F91: 22.605 | G91: 4.6 | H91: 200 | I91: 114.7 | J91: 78.2 | K91: 212 | L91: 3.958 | M91: 19 | N91: 21 | O91: 7/24/2012 | P91: 80.657696
A92: Mercury | B92: Mountaineer | C92: 27.609 | D92: 20.43 | E92: Car | F92: 27.56 | G92: 4 | H92: 210 | I92: 111.6 | J92: 70.2 | K92: 190.1 | L92: 3.876 | M92: 21 | N92: 18 | O92: 2/13/2008 | P92: 85.949744
... A97: Mercedes-B | B97: SL-Class | C97: 3.311 | D97: 58.6 | E97: Passenger | F97: 82.6 | G97: 5 | H97: 302 | I97: 99 | J97: 71.3 | K97: 177.1 | L97: 4.125 | M97: 21.1 | N97: 20 | O97: 3/17/2011 | P97: 139.98229
A98: Mercedes-B | B98: SLK | C98: 7.998 | E98: Passenger | F98: 38.9 | G98: 2.3 | H98: 190 | I98: 94.5 | J98: 67.5 | K98: 157.9 | L98: 3.055 | M98: 15.9 | N98: 26 | O98: 1/16/2011 | P98: 82.807362
A99: Mercedes-B | B99: SLK230 | C99: 1.526 | E99: Passenger | F99: 41 | G99: 2.3 | H99: 185 | I99: 94.5 | J99: 67.5 | K99: 157.3 | L99: 2.975 | M99: 14 | N99: 27 | O99: 8/6/2011 | P99: 81.848969
A100: Mercedes-B | B100: CLK Coupe | C100: 11.592 | E100: Passenger | F100: 41.6 | G100: 3.2 | H100: 215 | I100: 105.9 | J100: 67.8 | K100: 180.3 | L100: 3.213 | M100: 16.4 | N100: 26 | O100: 7/8/2011 | P100: 92.925792
A101: Mercedes-B | B101: CL500 | C101: 0.954 | E101: Passenger | F101: 85.5 | G101: 5 | H101: 302 | I101: 113.6 | J101: 73.1 | K101: 196.6 | L101: 4.115 | M101: 23.2 | N101: 20 | O101: 4/11/2011 | P101: 141.10098
A102: Mercedes-B | B102: M-Class | C102: 28.976 | E102: Car | F102: 35.3 | G102: 3.2 | H102: 215 | I102: 111 | J102: 72.2 | K102: 180.6 | L102: 4.387 | M102: 19 | N102: 20 | O102: 2/10/2011 | P102: 90.495532
A103: Nissan | B103: Sentra | C103: 42.643 | D103: 8.45 | E103: Passenger | F103: 13.499 | G103: 1.8 | H103: 126 | I103: 99.8 | J103: 67.3 | K103: 177.5 | L103: 2.593 | M103: 13.2 | N103: 30 | O103: 8/31/2011 | P103: 50.241978
A104: Nissan | B104: Altima | C104: 88.094 | D104: 11.295 | E104: Passenger | F104: 20.39 | G104: 2.4 | H104: 155 | I104: 103.1 | J104: 69.1 | K104: 183.5 | L104: 3.012 | M104: 15.9 | N104: 25 | O104: 8/2/2011 | P104: 63.313728
A105: Nissan | B105: Maxima | C105: 79.853 | D105: 15.125 | E105: Passenger | F105: 26.249 | G105: 3 | H105: 222 | I105: 108.3 | J105: 70.3 | K105: 190.5 | L105: 3.294 | M105: 18.5 | N105: 25 | O105: 5/6/2011 | P105: 89.42782
A106: Nissan | B106: Quest | C106: 27.308 | D106: 15.38 | E106: Car | F106: 26.399 | G106: 3.3 | H106: 170 | I106: 112.2 | J106: 74.9 | K106: 194.8 | L106: 3.991 | M106: 20 | N106: 21 | O106: 3/7/2011 | P106: 71.171664
...

Sheet Cleaned Data
A1: Manufacturer | B1: Model | C1: Vehicle_Segment | D1: Sales_Units_Thousands | E1: Price_Thousands_USD | F1: Engine_Size_L | G1: Horsepower | H1: Wheelbase_in | I1: Width_in | J1: Length_in | K1: Curb_Weight_Tons | L1: Fuel_Capacity_Gal | M1: Fuel_Efficiency_MPG | N1: Resale_Value_Thousands | O1: Launch_Date | P1: Launch_Year | Q1: Launch_Month | R1: Power_Perf_Factor | S1: Revenue_Millions_USD | T1: Price_Tier | U1: Data_Complete | V1: Sales_Rank | W1: Revenue_Rank
A2: Acura | B2: Integra | C2: Passenger Car | D2: 16.919 | E2: 21.5 | F2: 1.8 | G2: 140 | H2: 101.2 | I2: 67.3 | J2: 172.4 | K2: 2.639 | L2: 13.2 | M2: 28 | N2: 16.36 | O2: 40941 | P2: =YEAR(O2) -> 2012 | Q2: =TEXT(O2,"mmm") -> Feb | R2: 58.28015 | S2: =IFERROR(D2*E2,"") -> 363.7585 | T2: =IF(E2="","Unknown",_xlfn.IFS(E2<15,"Budget",E2<30,"Mid-range",TRUE(),"Luxury")) -> Mid-range | U2: =IF(COUNTBLANK(D2:R2)>0,"Incomplete","Complete") -> Complete | V2: =IFERROR(RANK(D2,$D$2:$D$158),"") -> 109 | W2: =IFERROR(RANK(S2,$S$2:$S$158),"") -> 119
A3: Acura | B3: TL | C3: Passenger Car | D3: 39.384 | E3: 28.4 | F3: 3.2 | G3: 225 | H3: 108.1 | I3: 70.3 | J3: 192.9 | K3: 3.517 | L3: 17.2 | M3: 25 | N3: 19.875 | O3: 40697 | P3: =YEAR(O3) -> 2011 | Q3: =TEXT(O3,"mmm") -> Jun | R3: 91.370778 | S3: =IFERROR(D3*E3,"") -> 1118.5056 | T3: =IF(E3="","Unknown",_xlfn.IFS(E3<15,"Budget",E3<30,"Mid-range",TRUE(),"Luxury")) -> Mid-range | U3: =IF(COUNTBLANK(D3:R3)>0,"Incomplete","Complete") -> Complete | V3: =IFERROR(RANK(D3,$D$2:$D$158),"") -> 64 | W3: =IFERROR(RANK(S3,$S$2:$S$158),"") -> 48
A4: Acura | B4: CL | C4: Passenger Car | D4: 14.114 | F4: 3.2 | G4: 225 | H4: 106.9 | I4: 70.6 | J4: 192 | K4: 3.47 | L4: 17.2 | M4: 26 | N4: 18.225 | O4: 40912 | P4: =YEAR(O4) -> 2012 | Q4: =TEXT(O4,"mmm") -> Jan | S4: =IFERROR(D4*E4,"") -> 0 | T4: =IF(E4="","Unknown",_xlfn.IFS(E4<15,"Budget",E4<30,"Mid-range",TRUE(),"Luxury")) -> Unknown | U4: =IF(COUNTBLANK(D4:R4)>0,"Incomplete","Complete") -> Incomplete | V4: =IFERROR(RANK(D4,$D$2:$D$158),"") -> 118 | W4: =IFERROR(RANK(S4,$S$2:$S$158),"") -> 156
A5: Acura | B5: RL | C5: Passenger Car | D5: 8.588 | E5: 42 | F5: 3.5 | G5: 210 | H5: 114.6 | I5: 71.4 | J5: 196.6 | K5: 3.85 | L5: 18 | M5: 22 | N5: 29.725 | O5: 40612 | P5: =YEAR(O5) -> 2011 | Q5: =TEXT(O5,"mmm") -> Mar | R5: 91.389779 | S5: =IFERROR(D5*E5,"") -> 360.696 | T5: =IF(E5="","Unknown",_xlfn.IFS(E5<15,"Budget",E5<30,"Mid-range",TRUE(),"Luxury")) -> Luxury | U5: =IF(COUNTBLANK(D5:R5)>0,"Incomplete","Complete") -> Complete | V5: =IFERROR(RANK(D5,$D$2:$D$158),"") -> 134 | W5: =IFERROR(RANK(S5,$S$2:$S$158),"") -> 120
A6: Audi | B6: A4 | C6: Passenger Car | D6: 20.397 | E6: 23.99 | F6: 1.8 | G6: 150 | H6: 102.6 | I6: 68.2 | J6: 178 | K6: 2.998 | L6: 16.4 | M6: 27 | N6: 22.255 | O6: 40824 | P6: =YEAR(O6) -> 2011 | Q6: =TEXT(O6,"mmm") -> Oct | R6: 62.777639 | S6: =IFERROR(D6*E6,"") -> 489.32403 | T6: =IF(E6="","Unknown",_xlfn.IFS(E6<15,"Budget",E6<30,"Mid-range",TRUE(),"Luxury")) -> Mid-range | U6: =IF(COUNTBLANK(D6:R6)>0,"Incomplete","Complete") -> Complete | V6: =IFERROR(RANK(D6,$D$2:$D$158),"") -> 97 | W6: =IFERROR(RANK(S6,$S$2:$S$158),"") -> 102
A7: Audi | B7: A6 | C7: Passenger Car | D7: 18.78 | E7: 33.95 | F7: 2.8 | G7: 200 | H7: 108.7 | I7: 76.1 | J7: 192 | K7: 3.561 | L7: 18.5 | M7: 22 | N7: 23.555 | O7: 40764 | P7: =YEAR(O7) -> 2011 | Q7: =TEXT(O7,"mmm") -> Aug | R7: 84.565105 | S7: =IFERROR(D7*E7,"") -> 637.581 | T7: =IF(E7="","Unknown",_xlfn.IFS(E7<15,"Budget",E7<30,"Mid-range",TRUE(),"Luxury")) -> Luxury | U7: =IF(COUNTBLANK(D7:R7)>0,"Incomplete","Complete") -> Complete | V7: =IFERROR(RANK(D7,$D$2:$D$158),"") -> 103 | W7: =IFERROR(RANK(S7,$S$2:$S$158),"") -> 86
A8: Audi | B8: A8 | C8: Passenger Car | D8: 1.38 | E8: 62 | F8: 4.2 | G8: 310 | H8: 113 | I8: 74 | J8: 198.2 | K8: 3.902 | L8: 23.7 | M8: 21 | N8: 39 | O8: 40966 | P8: =YEAR(O8) -> 2012 | Q8: =TEXT(O8,"mmm") -> Feb | R8: 134.65686 | S8: =IFERROR(D8*E8,"") -> 85.56 | T8: =IF(E8="","Unknown",_xlfn.IFS(E8<15,"Budget",E8<30,"Mid-range",TRUE(),"Luxury")) -> Luxury | U8: =IF(COUNTBLANK(D8:R8)>0,"Incomplete","Complete") -> Complete | V8: =IFERROR(RANK(D8,$D$2:$D$158),"") -> 152 | W8: =IFERROR(RANK(S8,$S$2:$S$158),"") -> 147
A9: BMW | B9: 323i | C9: Passenger Car | D9: 19.747 | E9: 26.99 | F9: 2.5 | G9: 170 | H9: 107.3 | I9: 68.4 | J9: 176 | K9: 3.179 | L9: 16.6 | M9: 26 | O9: 40722 | P9: =YEAR(O9) -> 2011 | Q9: =TEXT(O9,"mmm") -> Jun | R9: 71.191207 | S9: =IFERROR(D9*E9,"") -> 532.97153 | T9: =IF(E9="","Unknown",_xlfn.IFS(E9<15,"Budget",E9<30,"Mid-range",TRUE(),"Luxury")) -> Mid-range | U9: =IF(COUNTBLANK(D9:R9)>0,"Incomplete","Complete") -> Incomplete | V9: =IFERROR(RANK(D9,$D$2:$D$158),"") -> 101 | W9: =IFERROR(RANK(S9,$S$2:$S$158),"") -> 96
A10: BMW | B10: 328i | C10: Passenger Car | D10: 9.231 | E10: 33.4 | F10: 2.8 | G10: 193 | H10: 107.3 | I10: 68.5 | J10: 176 | K10: 3.197 | L10: 16.6 | M10: 24 | N10: 28.675 | O10: 40937 | P10: =YEAR(O10) -> 2012 | Q10: =TEXT(O10,"mmm") -> Jan | R10: 81.877069 | S10: =IFERROR(D10*E10,"") -> 308.3154 | T10: =IF(E10="","Unknown",_xlfn.IFS(E10<15,"Budget",E10<30,"Mid-range",TRUE(),"Luxury")) -> Luxury | U10: =IF(COUNTBLANK(D10:R10)>0,"Incomplete","Complete") -> Complete | V10: =IFERROR(RANK(D10,$D$2:$D$158),"") -> 130 | W10: =IFERROR(RANK(S10,$S$2:$S$158),"") -> 128
A11: BMW | B11: 528i | C11: Passenger Car | D11: 17.527 | E11: 38.9 | F11: 2.8 | G11: 193 | H11: 111.4 | I11: 70.9 | J11: 188 | K11: 3.472 | L11: 18.5 | M11: 25 | N11: 36.125 | O11: 40637 | P11: =YEAR(O11) -> 2011 | Q11: =TEXT(O11,"mmm") -> Apr | R11: 83.998724 | S11: =IFERROR(D11*E11,"") -> 681.8003 | T11: =IF(E11="","Unknown",_xlfn.IFS(E11<15,"Budget",E11<30,"Mid-range",TRUE(),"Luxury")) -> Luxury | U11: =IF(COUNTBLANK(D11:R11)>0,"Incomplete","Complete") -> Complete | V11: =IFERROR(RANK(D11,$D$2:$D$158),"") -> 107 | W11: =IFERROR(RANK(S11,$S$2:$S$158),"") -> 82
A12: Buick | B12: Century | C12: Passenger Car | D12: 91.561 | E12: 21.975 | F12: 3.1 | G12: 175 | H12: 109 | I12: 72.7 | J12: 194.6 | K12: 3.368 | L12: 17.5 | M12: 25 | N12: 12.475 | O12: 40849 | P12: =YEAR(O12) -> 2011 | Q12: =TEXT(O12,"mmm") -> Nov | R12: 71.181451 | S12: =IFERROR(D12*E12,"") -> 2012.053 | T12: =IF(E12="","Unknown",_xlfn.IFS(E12<15,"Budget",E12<30,"Mid-range",TRUE(),"Luxury")) -> Mid-range | U12: =IF(COUNTBLANK(D12:R12)>0,"Incomplete","Complete") -> Complete | V12: =IFERROR(RANK(D12,$D$2:$D$158),"") -> 23 | W12: =IFERROR(RANK(S12,$S$2:$S$158),"") -> 23
A13: Buick | B13: Regal | C13: Passenger Car | D13: 39.35 | E13: 25.3 | F13: 3.8 | G13: 240 | H13: 109 | I13: 72.7 | J13: 196.2 | K13: 3.543 | L13: 17.5 | M13: 23 | N13: 13.74 | O13: 40789 | P13: =YEAR(O13) -> 2011 | Q13: =TEXT(O13,"mmm") -> Sep | R13: 95.636703 | S13: =IFERROR(D13*E13,"") -> 995.555 | T13: =IF(E13="","Unknown",_xlfn.IFS(E13<15,"Budget",E13<30,"Mid-range",TRUE(),"Luxury")) -> Mid-range | U13: =IF(COUNTBLANK(D13:R13)>0,"Incomplete","Complete") -> Complete | V13: =IFERROR(RANK(D13,$D$2:$D$158),"") -> 65 | W13: =IFERROR(RANK(S13,$S$2:$S$158),"") -> 54
A14: Buick | B14: Park Avenue | C14: Passenger Car | D14: 27.851 | E14: 31.965 | F14: 3.8 | G14: 205 | H14: 113.8 | I14: 74.7 | J14: 206.8 | K14: 3.778 | L14: 18.5 | M14: 24 | N14: 20.19 | O14: 40991 | P14: =YEAR(O14) -> 2012 | Q14: =TEXT(O14,"mmm") -> Mar | R14: 85.828408 | S14: =IFERROR(D14*E14,"") -> 890.25721 | T14: =IF(E14="","Unknown",_xlfn.IFS(E14<15,"Budget",E14<30,"Mid-range",TRUE(),"Luxury")) -> Luxury | U14: =IF(COUNTBLANK(D14:R14)>0,"Incomplete","Complete") -> Complete | V14: =IFERROR(RANK(D14,$D$2:$D$158),"") -> 81 | W14: =IFERROR(RANK(S14,$S$2:$S$158),"") -> 61
A15: Buick | B15: LeSabre | C15: Passenger Car | D15: 83.257 | E15: 27.885 | F15: 3.8 | G15: 205 | H15: 112.2 | I15: 73.5 | J15: 200 | K15: 3.591 | L15: 17.5 | M15: 25 | N15: 13.36 | O15: 40747 | P15: =YEAR(O15) -> 2011 | Q15: =TEXT(O15,"mmm") -> Jul | R15: 84.254526 | S15: =IFERROR(D15*E15,"") -> 2321.6214 | T15: =IF(E15="","Unknown",_xlfn.IFS(E15<15,"Budget",E15<30,"Mid-range",TRUE(),"Luxury")) -> Mid-range | U15: =IF(COUNTBLANK(D15:R15)>0,"Incomplete","Complete") -> Complete | V15: =IFERROR(RANK(D15,$D$2:$D$158),"") -> 28 | W15: =IFERROR(RANK(S15,$S$2:$S$158),"") -> 17
A16: Cadillac | B16: DeVille | C16: Passenger Car | D16: 63.729 | E16: 39.895 | F16: 4.6 | G16: 275 | H16: 115.3 | I16: 74.5 | J16: 207.2 | K16: 3.978 | L16: 18.5 | M16: 22 | N16: 22.525 | O16: 40962 | P16: =YEAR(O16) -> 2012 | Q16: =TEXT(O16,"mmm") -> Feb | R16: 113.8546 | S16: =IFERROR(D16*E16,"") -> 2542.4685 | T16: =IF(E16="","Unknown",_xlfn.IFS(E16<15,"Budget",E16<30,"Mid-range",TRUE(),"Luxury")) -> Luxury | U16: =IF(COUNTBLANK(D16:R16)>0,"Incomplete","Complete") -> Complete | V16: =IFERROR(RANK(D16,$D$2:$D$158),"") -> 45 | W16: =IFERROR(RANK(S16,$S$2:$S$158),"") -> 15
A17: Cadillac | B17: Seville | C17: Passenger Car | D17: 15.943 | E17: 44.475 | F17: 4.6 | G17: 275 | H17: 112.2 | I17: 75 | J17: 201 | L17: 18.5 | M17: 22 | N17: 27.1 | O17: 40662 | P17: =YEAR(O17) -> 2011 | Q17: =TEXT(O17,"mmm") -> Apr | R17: 115.62136 | S17: =IFERROR(D17*E17,"") -> 709.06493 | T17: =IF(E17="","Unknown",_xlfn.IFS(E17<15,"Budget",E17<30,"Mid-range",TRUE(),"Luxury")) -> Luxury | U17: =IF(COUNTBLANK(D17:R17)>0,"Incomplete","Complete") -> Incomplete | V17: =IFERROR(RANK(D17,$D$2:$D$158),"") -> 112 | W17: =IFERROR(RANK(S17,$S$2:$S$158),"") -> 77
A18: Cadillac | B18: Eldorado | C18: Passenger Car | D18: 6.536 | E18: 39.665 | F18: 4.6 | G18: 275 | H18: 108 | I18: 75.5 | J18: 200.6 | K18: 3.843 | L18: 19 | M18: 22 | N18: 25.725 | O18: 40874 | P18: =YEAR(O18) -> 2011 | Q18: =TEXT(O18,"mmm") -> Nov | R18: 113.76587 | S18: =IFERROR(D18*E18,"") -> 259.25044 | T18: =IF(E18="","Unknown",_xlfn.IFS(E18<15,"Budget",E18<30,"Mid-range",TRUE(),"Luxury")) -> Luxury | U18: =IF(COUNTBLANK(D18:R18)>0,"Incomplete","Complete") -> Complete | V18: =IFERROR(RANK(D18,$D$2:$D$158),"") -> 138 | W18: =IFERROR(RANK(S18,$S$2:$S$158),"") -> 132
A19: Cadillac | B19: Catera | C19: Passenger Car | D19: 11.185 | E19: 31.01 | F19: 3 | G19: 200 | H19: 107.4 | I19: 70.3 | J19: 194.8 | K19: 3.77 | L19: 18 | M19: 22 | N19: 18.225 | O19: 40814 | P19: =YEAR(O19) -> 2011 | Q19: =TEXT(O19,"mmm") -> Sep | R19: 83.483094 | S19: =IFERROR(D19*E19,"") -> 346.84685 | T19: =IF(E19="","Unknown",_xlfn.IFS(E19<15,"Budget",E19<30,"Mid-range",TRUE(),"Luxury")) -> Luxury | U19: =IF(COUNTBLANK(D19:R19)>0,"Incomplete","Complete") -> Complete | V19: =IFERROR(RANK(D19,$D$2:$D$158),"") -> 126 | W19: =IFERROR(RANK(S19,$S$2:$S$158),"") -> 123
A20: Cadillac | B20: Escalade | C20: SUV/Truck/Van | D20: 14.785 | E20: 46.225 | F20: 5.7 | G20: 255 | H20: 117.5 | I20: 77 | J20: 201.2 | K20: 5.572 | L20: 30 | M20: 15 | O20: 41016 | P20: =YEAR(O20) -> 2012 | Q20: =TEXT(O20,"mmm") -> Apr | R20: 109.50912 | S20: =IFERROR(D20*E20,"") -> 683.43663 | T20: =IF(E20="","Unknown",_xlfn.IFS(E20<15,"Budget",E20<30,"Mid-range",TRUE(),"Luxury")) -> Luxury | U20: =IF(COUNTBLANK(D20:R20)>0,"Incomplete","Complete") -> Incomplete | V20: =IFERROR(RANK(D20,$D$2:$D$158),"") -> 115 | W20: =IFERROR(RANK(S20,$S$2:$S$158),"") -> 80
A21: Chevrolet | B21: Cavalier | C21: Passenger Car | D21: 145.519 | E21: 13.26 | F21: 2.2 | G21: 115 | H21: 104.1 | I21: 67.9 | J21: 180.9 | K21: 2.676 | L21: 14.3 | M21: 27 | N21: 9.25 | O21: 40772 | P21: =YEAR(O21) -> 2011 | Q21: =TEXT(O21,"mmm") -> Aug | R21: 46.363347 | S21: =IFERROR(D21*E21,"") -> 1929.5819 | T21: =IF(E21="","Unknown",_xlfn.IFS(E21<15,"Budget",E21<30,"Mid-range",TRUE(),"Luxury")) -> Budget | U21: =IF(COUNTBLANK(D21:R21)>0,"Incomplete","Complete") -> Complete | V21: =IFERROR(RANK(D21,$D$2:$D$158),"") -> 13 | W21: =IFERROR(RANK(S21,$S$2:$S$158),"") -> 27
A22: Chevrolet | B22: Malibu | C22: Passenger Car | D22: 135.126 | E22: 16.535 | F22: 3.1 | G22: 170 | H22: 107 | I22: 69.4 | J22: 190.4 | K22: 3.051 | L22: 15 | M22: 25 | N22: 11.225 | O22: 40987 | P22: =YEAR(O22) -> 2012 | Q22: =TEXT(O22,"mmm") -> Mar | R22: 67.314462 | S22: =IFERROR(D22*E22,"") -> 2234.3084 | T22: =IF(E22="","Unknown",_xlfn.IFS(E22<15,"Budget",E22<30,"Mid-range",TRUE(),"Luxury")) -> Mid-range | U22: =IF(COUNTBLANK(D22:R22)>0,"Incomplete","Complete") -> Complete | V22: =IFERROR(RANK(D22,$D$2:$D$158),"") -> 15 | W22: =IFERROR(RANK(S22,$S$2:$S$158),"") -> 18
A23: Chevrolet | B23: Lumina | C23: Passenger Car | D23: 24.629 | E23: 18.89 | F23: 3.1 | G23: 175 | H23: 107.5 | I23: 72.5 | J23: 200.9 | K23: 3.33 | L23: 16.6 | M23: 25 | N23: 10.31 | O23: 40687 | P23: =YEAR(O23) -> 2011 | Q23: =TEXT(O23,"mmm") -> May | R23: 69.991396 | S23: =IFERROR(D23*E23,"") -> 465.24181 | T23: =IF(E23="","Unknown",_xlfn.IFS(E23<15,"Budget",E23<30,"Mid-range",TRUE(),"Luxury")) -> Mid-range | U23: =IF(COUNTBLANK(D23:R23)>0,"Incomplete","Complete") -> Complete | V23: =IFERROR(RANK(D23,$D$2:$D$158),"") -> 89 | W23: =IFERROR(RANK(S23,$S$2:$S$158),"") -> 105
A24: Chevrolet | B24: Monte Carlo | C24: Passenger Car | D24: 42.593 | E24: 19.39 | F24: 3.4 | G24: 180 | H24: 110.5 | I24: 72.7 | J24: 197.9 | K24: 3.34 | L24: 17 | M24: 27 | N24: 11.525 | O24: 40899 | P24: =YEAR(O24) -> 2011 | Q24: =TEXT(O24,"mmm") -> Dec | R24: 72.030917 | S24: =IFERROR(D24*E24,"") -> 825.87827 | T24: =IF(E24="","Unknown",_xlfn.IFS(E24<15,"Budget",E24<30,"Mid-range",TRUE(),"Luxury")) -> Mid-range | U24: =IF(COUNTBLANK(D24:R24)>0,"Incomplete","Complete") -> Complete | V24: =IFERROR(RANK(D24,$D$2:$D$158),"") -> 59 | W24: =IFERROR(RANK(S24,$S$2:$S$158),"") -> 66
A25: Chevrolet | B25: Camaro | C25: Passenger Car | D25: 26.402 | E25: 24.34 | F25: 3.8 | G25: 200 | H25: 101.1 | I25: 74.1 | J25: 193.2 | K25: 3.5 | L25: 16.8 | M25: 25 | N25: 13.025 | O25: 40839 | P25: =YEAR(O25) -> 2011 | Q25: =TEXT(O25,"mmm") -> Oct | R25: 81.118543 | S25: =IFERROR(D25*E25,"") -> 642.62468 | T25: =IF(E25="","Unknown",_xlfn.IFS(E25<15,"Budget",E25<30,"Mid-range",TRUE(),"Luxury")) -> Mid-range | U25: =IF(COUNTBLANK(D25:R25)>0,"Incomplete","Complete") -> Complete | V25: =IFERROR(RANK(D25,$D$2:$D$158),"") -> 86 | W25: =IFERROR(RANK(S25,$S$2:$S$158),"") -> 85
A26: Chevrolet | B26: Corvette | C26: Passenger Car | D26: 17.947 | E26: 45.705 | F26: 5.7 | G26: 345 | H26: 104.5 | I26: 73.6 | J26: 179.7 | K26: 3.21 | L26: 19.1 | M26: 22 | N26: 36.225 | O26: 41041 | P26: =YEAR(O26) -> 2012 | Q26: =TEXT(O26,"mmm") -> May | R26: 141.14115 | S26: =IFERROR(D26*E26,"") -> 820.26763 | T26: =IF(E26="","Unknown",_xlfn.IFS(E26<15,"Budget",E26<30,"Mid-range",TRUE(),"Luxury")) -> Luxury | U26: =IF(COUNTBLANK(D26:R26)>0,"Incomplete","Complete") -> Complete | V26: =IFERROR(RANK(D26,$D$2:$D$158),"") -> 105 | W26: =IFERROR(RANK(S26,$S$2:$S$158),"") -> 67
A27: Chevrolet | B27: Prizm | C27: Passenger Car | D27: 32.299 | E27: 13.96 | F27: 1.8 | G27: 120 | H27: 97.1 | I27: 66.7 | J27: 174.3 | K27: 2.398 | L27: 13.2 | M27: 33 | N27: 9.125 | O27: 40797 | P27: =YEAR(O27) -> 2011 | Q27: =TEXT(O27,"mmm") -> Sep | R27: 48.297636 | S27: =IFERROR(D27*E27,"") -> 450.89404 | T27: =IF(E27="","Unknown",_xlfn.IFS(E27<15,"Budget",E27<30,"Mid-range",TRUE(),"Luxury")) -> Budget | U27: =IF(COUNTBLANK(D27:R27)>0,"Incomplete","Complete") -> Complete | V27: =IFERROR(RANK(D27,$D$2:$D$158),"") -> 75 | W27: =IFERROR(RANK(S27,$S$2:$S$158),"") -> 108
A28: Chevrolet | B28: Metro | C28: Passenger Car | D28: 21.855 | E28: 9.235 | F28: 1 | G28: 55 | H28: 93.1 | I28: 62.6 | J28: 149.4 | K28: 1.895 | L28: 10.3 | M28: 45 | N28: 5.16 | O28: 41012 | P28: =YEAR(O28) -> 2012 | Q28: =TEXT(O28,"mmm") -> Apr | R28: 23.276272 | S28: =IFERROR(D28*E28,"") -> 201.83092 | T28: =IF(E28="","Unknown",_xlfn.IFS(E28<15,"Budget",E28<30,"Mid-range",TRUE(),"Luxury")) -> Budget | U28: =IF(COUNTBLANK(D28:R28)>0,"Incomplete","Complete") -> Complete | V28: =IFERROR(RANK(D28,$D$2:$D$158),"") -> 96 | W28: =IFERROR(RANK(S28,$S$2:$S$158),"") -> 134
A29: Chevrolet | B29: Impala | C29: Passenger Car | D29: 107.995 | E29: 18.89 | F29: 3.4 | G29: 180 | H29: 110.5 | I29: 73 | J29: 200 | K29: 3.389 | L29: 17 | M29: 27 | O29: 40712 | P29: =YEAR(O29) -> 2011 | Q29: =TEXT(O29,"mmm") -> Jun | R29: 71.838039 | S29: =IFERROR(D29*E29,"") -> 2040.0256 | T29: =IF(E29="","Unknown",_xlfn.IFS(E29<15,"Budget",E29<30,"Mid-range",TRUE(),"Luxury")) -> Mid-range | U29: =IF(COUNTBLANK(D29:R29)>0,"Incomplete","Complete") -> Incomplete | V29: =IFERROR(RANK(D29,$D$2:$D$158),"") -> 20 | W29: =IFERROR(RANK(S29,$S$2:$S$158),"") -> 22
A30: Chrysler | B30: Sebring Coupe | C30: Passenger Car | D30: 7.854 | E30: 19.84 | F30: 2.5 | G30: 163 | H30: 103.7 | I30: 69.7 | J30: 190.9 | K30: 2.967 | L30: 15.9 | M30: 24 | N30: 12.36 | O30: 40924 | P30: =YEAR(O30) -> 2012 | Q30: =TEXT(O30,"mmm") -> Jan | R30: 65.957184 | S30: =IFERROR(D30*E30,"") -> 155.82336 | T30: =IF(E30="","Unknown",_xlfn.IFS(E30<15,"Budget",E30<30,"Mid-range",TRUE(),"Luxury")) -> Mid-range | U30: =IF(COUNTBLANK(D30:R30)>0,"Incomplete","Complete") -> Complete | V30: =IFERROR(RANK(D30,$D$2:$D$158),"") -> 137 | W30: =IFERROR(RANK(S30,$S$2:$S$158),"") -> 138
A31: Chrysler | B31: Sebring Conv. | C31: Passenger Car | D31: 32.775 | E31: 24.495 | F31: 2.5 | G31: 168 | H31: 106 | I31: 69.2 | J31: 193 | K31: 3.332 | L31: 16 | M31: 24 | N31: 14.18 | O31: 40864 | P31: =YEAR(O31) -> 2011 | Q31: =TEXT(O31,"mmm") -> Nov | R31: 69.521355 | S31: =IFERROR(D31*E31,"") -> 802.82362 | T31: =IF(E31="","Unknown",_xlfn.IFS(E31<15,"Budget",E31<30,"Mid-range",TRUE(),"Luxury")) -> Mid-range | U31: =IF(COUNTBLANK(D31:R31)>0,"Incomplete","Complete") -> Complete | V31: =IFERROR(RANK(D31,$D$2:$D$158),"") -> 72 | W31: =IFERROR(RANK(S31,$S$2:$S$158),"") -> 70
A32: Chrysler | B32: Concorde | C32: Passenger Car | D32: 31.148 | E32: 22.245 | F32: 2.7 | G32: 200 | H32: 113 | I32: 74.4 | J32: 209.1 | K32: 3.452 | L32: 17 | M32: 26 | N32: 13.725 | O32: 41066 | P32: =YEAR(O32) -> 2012 | Q32: =TEXT(O32,"mmm") -> Jun | R32: 80.023782 | S32: =IFERROR(D32*E32,"") -> 692.88726 | T32: =IF(E32="","Unknown",_xlfn.IFS(E32<15,"Budget",E32<30,"Mid-range",TRUE(),"Luxury")) -> Mid-range | U32: =IF(COUNTBLANK(D32:R32)>0,"Incomplete","Complete") -> Complete | V32: =IFERROR(RANK(D32,$D$2:$D$158),"") -> 76 | W32: =IFERROR(RANK(S32,$S$2:$S$158),"") -> 79
A33: Chrysler | B33: Cirrus | C33: Passenger Car | D33: 32.306 | E33: 16.48 | F33: 2 | G33: 132 | H33: 108 | I33: 71 | J33: 186 | K33: 2.911 | L33: 16 | M33: 27 | N33: 12.64 | O33: 40822 | P33: =YEAR(O33) -> 2011 | Q33: =TEXT(O33,"mmm") -> Oct | R33: 53.5662 | S33: =IFERROR(D33*E33,"") -> 532.40288 | T33: =IF(E33="","Unknown",_xlfn.IFS(E33<15,"Budget",E33<30,"Mid-range",TRUE(),"Luxury")) -> Mid-range | U33: =IF(COUNTBLANK(D33:R33)>0,"Incomplete","Complete") -> Complete | V33: =IFERROR(RANK(D33,$D$2:$D$158),"") -> 74 | W33: =IFERROR(RANK(S33,$S$2:$S$158),"") -> 97
A34: Chrysler | B34: LHS | C34: Passenger Car | D34: 13.462 | E34: 28.34 | F34: 3.5 | G34: 253 | H34: 113 | I34: 74.4 | J34: 207.7 | K34: 3.564 | L34: 17 | M34: 23 | N34: 17.325 | O34: 41037 | P34: =YEAR(O34) -> 2012 | Q34: =TEXT(O34,"mmm") -> May | R34: 101.32928 | S34: =IFERROR(D34*E34,"") -> 381.51308 | T34: =IF(E34="","Unknown",_xlfn.IFS(E34<15,"Budget",E34<30,"Mid-range",TRUE(),"Luxury")) -> Mid-range | U34: =IF(COUNTBLANK(D34:R34)>0,"Incomplete","Complete") -> Complete | V34: =IFERROR(RANK(D34,$D$2:$D$158),"") -> 120 | W34: =IFERROR(RANK(S34,$S$2:$S$158),"") -> 116
A35: Chrysler | B35: Town & Country | C35: SUV/Truck/Van | D35: 53.48 | N35: 19.54 | O35: 40737 | P35: =YEAR(O35) -> 2011 | Q35: =TEXT(O35,"mmm") -> Jul | S35: =IFERROR(D35*E35,"") -> 0 | T35: =IF(E35="","Unknown",_xlfn.IFS(E35<15,"Budget",E35<30,"Mid-range",TRUE(),"Luxury")) -> Unknown | U35: =IF(COUNTBLANK(D35:R35)>0,"Incomplete","Complete") -> Incomplete | V35: =IFERROR(RANK(D35,$D$2:$D$158),"") -> 50 | W35: =IFERROR(RANK(S35,$S$2:$S$158),"") -> 156
A36: Chrysler | B36: 300M | C36: Passenger Car | D36: 30.696 | E36: 29.185 | F36: 3.5 | G36: 253 | H36: 113 | I36: 74.4 | J36: 197.8 | K36: 3.567 | L36: 17 | M36: 23 | O36: 40949 | P36: =YEAR(O36) -> 2012 | Q36: =TEXT(O36,"mmm") -> Feb | R36: 101.65524 | S36: =IFERROR(D36*E36,"") -> 895.86276 | T36: =IF(E36="","Unknown",_xlfn.IFS(E36<15,"Budget",E36<30,"Mid-range",TRUE(),"Luxury")) -> Mid-range | U36: =IF(COUNTBLANK(D36:R36)>0,"Incomplete","Complete") -> Incomplete | V36: =IFERROR(RANK(D36,$D$2:$D$158),"") -> 78 | W36: =IFERROR(RANK(S36,$S$2:$S$158),"") -> 60
A37: Dodge | B37: Neon | C37: Passenger Car | D37: 76.034 | E37: 12.64 | F37: 2 | G37: 132 | H37: 105 | I37: 74.4 | J37: 174.4 | K37: 2.567 | L37: 12.5 | M37: 29 | N37: 7.75 | O37: 40889 | P37: =YEAR(O37) -> 2011 | Q37: =TEXT(O37,"mmm") -> Dec | R37: 52.084899 | S37: =IFERROR(D37*E37,"") -> 961.06976 | T37: =IF(E37="","Unknown",_xlfn.IFS(E37<15,"Budget",E37<30,"Mid-range",TRUE(),"Luxury")) -> Budget | U37: =IF(COUNTBLANK(D37:R37)>0,"Incomplete","Complete") -> Complete | V37: =IFERROR(RANK(D37,$D$2:$D$158),"") -> 34 | W37: =IFERROR(RANK(S37,$S$2:$S$158),"") -> 58
A38: Dodge | B38: Avenger | C38: Passenger Car | D38: 4.734 | E38: 19.045 | F38: 2.5 | G38: 163 | H38: 103.7 | I38: 69.1 | J38: 190.2 | K38: 2.879 | L38: 15.9 | M38: 24 | N38: 12.545 | O38: 41091 | P38: =YEAR(O38) -> 2012 | Q38: =TEXT(O38,"mmm") -> Jul | R38: 65.650508 | S38: =IFERROR(D38*E38,"") -> 90.15903 | T38: =IF(E38="","Unknown",_xlfn.IFS(E38<15,"Budget",E38<30,"Mid-range",TRUE(),"Luxury")) -> Mid-range | U38: =IF(COUNTBLANK(D38:R38)>0,"Incomplete","Complete") -> Complete | V38: =IFERROR(RANK(D38,$D$2:$D$158),"") -> 144 | W38: =IFERROR(RANK(S38,$S$2:$S$158),"") -> 145
A39: Dodge | B39: Stratus | C39: Passenger Car | D39: 71.186 | E39: 20.23 | F39: 2.5 | G39: 168 | H39: 108 | I39: 71 | J39: 186 | K39: 3.058 | L39: 16 | M39: 24 | N39: 10.185 | O39: 40847 | P39: =YEAR(O39) -> 2011 | Q39: =TEXT(O39,"mmm") -> Oct | R39: 67.876108 | S39: =IFERROR(D39*E39,"") -> 1440.0928 | T39: =IF(E39="","Unknown",_xlfn.IFS(E39<15,"Budget",E39<30,"Mid-range",TRUE(),"Luxury")) -> Mid-range | U39: =IF(COUNTBLANK(D39:R39)>0,"Incomplete","Complete") -> Complete | V39: =IFERROR(RANK(D39,$D$2:$D$158),"") -> 37 | W39: =IFERROR(RANK(S39,$S$2:$S$158),"") -> 39
A40: Dodge | B40: Intrepid | C40: Passenger Car | D40: 88.028 | E40: 22.505 | F40: 2.7 | G40: 202 | H40: 113 | I40: 74.7 | J40: 203.7 | K40: 3.489 | L40: 17 | N40: 12.275 | O40: 41062 | P40: =YEAR(O40) -> 2012 | Q40: =TEXT(O40,"mmm") -> Jun | R40: 80.83147 | S40: =IFERROR(D40*E40,"") -> 1981.0701 | T40: =IF(E40="","Unknown",_xlfn.IFS(E40<15,"Budget",E40<30,"Mid-range",TRUE(),"Luxury")) -> Mid-range | U40: =IF(COUNTBLANK(D40:R40)>0,"Incomplete","Complete") -> Incomplete | V40: =IFERROR(RANK(D40,$D$2:$D$158),"") -> 25 | W40: =IFERROR(RANK(S40,$S$2:$S$158),"") -> 25
A41: Dodge | B41: Viper | C41: Passenger Car | D41: 0.916 | E41: 69.725 | F41: 8 | G41: 450 | H41: 96.2 | I41: 75.7 | J41: 176.7 | K41: 3.375 | L41: 19 | M41: 16 | N41: 58.47 | O41: 40762 | P41: =YEAR(O41) -> 2011 | Q41: =TEXT(O41,"mmm") -> Aug | R41: 188.14432 | S41: =IFERROR(D41*E41,"") -> 63.8681 | T41: =IF(E41="","Unknown",_xlfn.IFS(E41<15,"Budget",E41<30,"Mid-range",TRUE(),"Luxury")) -> Luxury | U41: =IF(COUNTBLANK(D41:R41)>0,"Incomplete","Complete") -> Complete | V41: =IFERROR(RANK(D41,$D$2:$D$158),"") -> 156 | W41: =IFERROR(RANK(S41,$S$2:$S$158),"") -> 152
A42: Dodge | B42: Ram Pickup | C42: SUV/Truck/Van | D42: 227.061 | E42: 19.46 | F42: 5.2 | G42: 230 | H42: 138.7 | I42: 79.3 | J42: 224.2 | K42: 4.47 | L42: 26 | M42: 17 | N42: 15.06 | O42: 40974 | P42: =YEAR(O42) -> 2012 | Q42: =TEXT(O42,"mmm") -> Mar | R42: 90.2117 | S42: =IFERROR(D42*E42,"") -> 4418.6071 | T42: =IF(E42="","Unknown",_xlfn.IFS(E42<15,"Budget",E42<30,"Mid-range",TRUE(),"Luxury")) -> Mid-range | U42: =IF(COUNTBLANK(D42:R42)>0,"Incomplete","Complete") -> Complete | V42: =IFERROR(RANK(D42,$D$2:$D$158),"") -> 6 | W42: =IFERROR(RANK(S42,$S$2:$S$158),"") -> 4
A43: Dodge | B43: Ram Wagon | C43: SUV/Truck/Van | D43: 16.767 | E43: 21.315 | F43: 3.9 | G43: 175 | H43: 109.6 | I43: 78.8 | J43: 192.6 | K43: 4.245 | L43: 32 | M43: 15 | N43: 15.51 | O43: 40914 | P43: =YEAR(O43) -> 2012 | Q43: =TEXT(O43,"mmm") -> Jan | R43: 71.135292 | S43: =IFERROR(D43*E43,"") -> 357.3886 | T43: =IF(E43="","Unknown",_xlfn.IFS(E43<15,"Budget",E43<30,"Mid-range",TRUE(),"Luxury")) -> Mid-range | U43: =IF(COUNTBLANK(D43:R43)>0,"Incomplete","Complete") -> Complete | V43: =IFERROR(RANK(D43,$D$2:$D$158),"") -> 111 | W43: =IFERROR(RANK(S43,$S$2:$S$158),"") -> 122
A44: Dodge | B44: Ram Van | C44: SUV/Truck/Van | D44: 31.038 | E44: 18.575 | F44: 3.9 | G44: 175 | H44: 127.2 | I44: 78.8 | J44: 208.5 | K44: 4.298 | L44: 32 | M44: 16 | N44: 13.425 | O44: 41116 | P44: =YEAR(O44) -> 2012 | Q44: =TEXT(O44,"mmm") -> Jul | R44: 70.078322 | S44: =IFERROR(D44*E44,"") -> 576.53085 | T44: =IF(E44="","Unknown",_xlfn.IFS(E44<15,"Budget",E44<30,"Mid-range",TRUE(),"Luxury")) -> Mid-range | U44: =IF(COUNTBLANK(D44:R44)>0,"Incomplete","Complete") -> Complete | V44: =IFERROR(RANK(D44,$D$2:$D$158),"") -> 77 | W44: =IFERROR(RANK(S44,$S$2:$S$158),"") -> 91
A45: Dodge | B45: Dakota | C45: SUV/Truck/Van | D45: 111.313 | E45: 16.98 | F45: 2.5 | G45: 120 | H45: 131 | I45: 71.5 | J45: 215 | K45: 3.557 | L45: 22 | M45: 19 | N45: 11.26 | O45: 40872 | P45: =YEAR(O45) -> 2011 | Q45: =TEXT(O45,"mmm") -> Nov | R45: 49.645002 | S45: =IFERROR(D45*E45,"") -> 1890.0947 | T45: =IF(E45="","Unknown",_xlfn.IFS(E45<15,"Budget",E45<30,"Mid-range",TRUE(),"Luxury")) -> Mid-range | U45: =IF(COUNTBLANK(D45:R45)>0,"Incomplete","Complete") -> Complete | V45: =IFERROR(RANK(D45,$D$2:$D$158),"") -> 19 | W45: =IFERROR(RANK(S45,$S$2:$S$158),"") -> 28
A46: Dodge | B46: Durango | C46: SUV/Truck/Van | D46: 101.323 | E46: 26.31 | F46: 5.2 | G46: 230 | H46: 115.7 | I46: 71.7 | J46: 193.5 | K46: 4.394 | L46: 25 | M46: 17 | O46: 41087 | P46: =YEAR(O46) -> 2012 | Q46: =TEXT(O46,"mmm") -> Jun | R46: 92.854125 | S46: =IFERROR(D46*E46,"") -> 2665.8081 | T46: =IF(E46="","Unknown",_xlfn.IFS(E46<15,"Budget",E46<30,"Mid-range",TRUE(),"Luxury")) -> Mid-range | U46: =IF(COUNTBLANK(D46:R46)>0,"Incomplete","Complete") -> Incomplete | V46: =IFERROR(RANK(D46,$D$2:$D$158),"") -> 21 | W46: =IFERROR(RANK(S46,$S$2:$S$158),"") -> 11
A47: Dodge | B47: Caravan | C47: SUV/Truck/Van | D47: 181.749 | E47: 19.565 | F47: 2.4 | G47: 150 | H47: 113.3 | I47: 76.8 | J47: 186.3 | K47: 3.533 | L47: 20 | M47: 24 | N47: 12.025 | O47: 40787 | P47: =YEAR(O47) -> 2011 | Q47: =TEXT(O47,"mmm") -> Sep | R47: 61.227 | S47: =IFERROR(D47*E47,"") -> 3555.9192 | T47: =IF(E47="","Unknown",_xlfn.IFS(E47<15,"Budget",E47<30,"Mid-range",TRUE(),"Luxury")) -> Mid-range | U47: =IF(COUNTBLANK(D47:R47)>0,"Incomplete","Complete") -> Complete | V47: =IFERROR(RANK(D47,$D$2:$D$158),"") -> 9 | W47: =IFERROR(RANK(S47,$S$2:$S$158),"") -> 8
A48: Ford | B48: Escort | C48: Passenger Car | D48: 70.227 | E48: 12.07 | F48: 2 | G48: 110 | H48: 98.4 | I48: 67 | J48: 174.7 | K48: 2.468 | L48: 12.7 | M48: 30 | N48: 7.425 | O48: 40999 | P48: =YEAR(O48) -> 2012 | Q48: =TEXT(O48,"mmm") -> Mar | R48: 44.083709 | S48: =IFERROR(D48*E48,"") -> 847.63989 | T48: =IF(E48="","Unknown",_xlfn.IFS(E48<15,"Budget",E48<30,"Mid-range",TRUE(),"Luxury")) -> Budget | U48: =IF(COUNTBLANK(D48:R48)>0,"Incomplete","Complete") -> Complete | V48: =IFERROR(RANK(D48,$D$2:$D$158),"") -> 38 | W48: =IFERROR(RANK(S48,$S$2:$S$158),"") -> 65
A49: Ford | B49: Mustang | C49: Passenger Car | D49: 113.369 | E49: 21.56 | F49: 3.8 | G49: 190 | H49: 101.3 | I49: 73.1 | J49: 183.2 | K49: 3.203 | L49: 15.7 | M49: 24 | N49: 12.76 | O49: 40939 | P49: =YEAR(O49) -> 2012 | Q49: =TEXT(O49,"mmm") -> Jan | R49: 76.509185 | S49: =IFERROR(D49*E49,"") -> 2444.2356 | T49: =IF(E49="","Unknown",_xlfn.IFS(E49<15,"Budget",E49<30,"Mid-range",TRUE(),"Luxury")) -> Mid-range | U49: =IF(COUNTBLANK(D49:R49)>0,"Incomplete","Complete") -> Complete | V49: =IFERROR(RANK(D49,$D$2:$D$158),"") -> 18 | W49: =IFERROR(RANK(S49,$S$2:$S$158),"") -> 16
A50: Ford | B50: Contour | C50: Passenger Car | D50: 35.068 | E50: 17.035 | F50: 2.5 | G50: 170 | H50: 106.5 | I50: 69.1 | J50: 184.6 | K50: 2.769 | L50: 15 | M50: 25 | N50: 8.835 | O50: 41141 | P50: =YEAR(O50) -> 2012 | Q50: =TEXT(O50,"mmm") -> Aug | R50: 67.351011 | S50: =IFERROR(D50*E50,"") -> 597.38338 | T50: =IF(E50="","Unknown",_xlfn.IFS(E50<15,"Budget",E50<30,"Mid-range",TRUE(),"Luxury")) -> Mid-range | U50: =IF(COUNTBLANK(D50:R50)>0,"Incomplete","Complete") -> Complete | V50: =IFERROR(RANK(D50,$D$2:$D$158),"") -> 69 | W50: =IFERROR(RANK(S50,$S$2:$S$158),"") -> 89
A51: Ford | B51: Taurus | C51: Passenger Car | D51: 245.815 | E51: 17.885 | F51: 3 | G51: 155 | H51: 108.5 | I51: 73 | J51: 197.6 | K51: 3.368 | L51: 16 | M51: 24 | N51: 10.055 | O51: 40897 | P51: =YEAR(O51) -> 2011 | Q51: =TEXT(O51,"mmm") -> Dec | R51: 62.50374 | S51: =IFERROR(D51*E51,"") -> 4396.4013 | T51: =IF(E51="","Unknown",_xlfn.IFS(E51<15,"Budget",E51<30,"Mid-range",TRUE(),"Luxury")) -> Mid-range | U51: =IF(COUNTBLANK(D51:R51)>0,"Incomplete","Complete") -> Complete | V51: =IFERROR(RANK(D51,$D$2:$D$158),"") -> 4 | W51: =IFERROR(RANK(S51,$S$2:$S$158),"") -> 5
A52: Ford | B52: Focus | C52: Passenger Car | D52: 175.67 | E52: 12.315 | F52: 2 | G52: 107 | H52: 103 | I52: 66.9 | J52: 174.8 | K52: 2.564 | L52: 13.2 | M52: 30 | O52: 41112 | P52: =YEAR(O52) -> 2012 | Q52: =TEXT(O52,"mmm") -> Jul | R52: 43.117132 | S52: =IFERROR(D52*E52,"") -> 2163.376 | T52: =IF(E52="","Unknown",_xlfn.IFS(E52<15,"Budget",E52<30,"Mid-range",TRUE(),"Luxury")) -> Budget | U52: =IF(COUNTBLANK(D52:R52)>0,"Incomplete","Complete") -> Incomplete | V52: =IFERROR(RANK(D52,$D$2:$D$158),"") -> 10 | W52: =IFERROR(RANK(S52,$S$2:$S$158),"") -> 19
A53: Ford | B53: Crown Victoria | C53: Passenger Car | D53: 63.403 | E53: 22.195 | F53: 4.6 | G53: 200 | H53: 114.7 | I53: 78.2 | J53: 212 | K53: 3.908 | L53: 19 | M53: 21 | N53: 14.21 | O53: 40812 | P53: =YEAR(O53) -> 2011 | Q53: =TEXT(O53,"mmm") -> Sep | R53: 80.499537 | S53: =IFERROR(D53*E53,"") -> 1407.2296 | T53: =IF(E53="","Unknown",_xlfn.IFS(E53<15,"Budget",E53<30,"Mid-range",TRUE(),"Luxury")) -> Mid-range | U53: =IF(COUNTBLANK(D53:R53)>0,"Incomplete","Complete") -> Complete | V53: =IFERROR(RANK(D53,$D$2:$D$158),"") -> 46 | W53: =IFERROR(RANK(S53,$S$2:$S$158),"") -> 40
A54: Ford | B54: Explorer | C54: SUV/Truck/Van | D54: 276.747 | E54: 31.93 | F54: 4 | G54: 210 | H54: 111.6 | I54: 70.2 | J54: 190.7 | K54: 3.876 | L54: 21 | M54: 19 | N54: 16.64 | O54: 41024 | P54: =YEAR(O54) -> 2012 | Q54: =TEXT(O54,"mmm") -> Apr | R54: 87.635496 | S54: =IFERROR(D54*E54,"") -> 8836.5317 | T54: =IF(E54="","Unknown",_xlfn.IFS(E54<15,"Budget",E54<30,"Mid-range",TRUE(),"Luxury")) -> Luxury | U54: =IF(COUNTBLANK(D54:R54)>0,"Incomplete","Complete") -> Complete | V54: =IFERROR(RANK(D54,$D$2:$D$158),"") -> 2 | W54: =IFERROR(RANK(S54,$S$2:$S$158),"") -> 2
A55: Ford | B55: Windstar | C55: SUV/Truck/Van | D55: 155.787 | E55: 21.41 | F55: 3 | G55: 150 | H55: 120.7 | I55: 76.6 | J55: 200.9 | K55: 3.761 | L55: 26 | M55: 21 | N55: 13.175 | O55: 40964 | P55: =YEAR(O55) -> 2012 | Q55: =TEXT(O55,"mmm") -> Feb | R55: 62.095048 | S55: =IFERROR(D55*E55,"") -> 3335.3997 | T55: =IF(E55="","Unknown",_xlfn.IFS(E55<15,"Budget",E55<30,"Mid-range",TRUE(),"Luxury")) -> Mid-range | U55: =IF(COUNTBLANK(D55:R55)>0,"Incomplete","Complete") -> Complete | V55: =IFERROR(RANK(D55,$D$2:$D$158),"") -> 12 | W55: =IFERROR(RANK(S55,$S$2:$S$158),"") -> 10
A56: Ford | B56: Expedition | C56: SUV/Truck/Van | D56: 125.338 | E56: 36.135 | F56: 4.6 | G56: 240 | H56: 119 | I56: 78.7 | J56: 204.6 | K56: 4.808 | L56: 26 | M56: 16 | N56: 23.575 | O56: 41166 | P56: =YEAR(O56) -> 2012 | Q56: =TEXT(O56,"mmm") -> Sep | R56: 100.0248 | S56: =IFERROR(D56*E56,"") -> 4529.0886 | T56: =IF(E56="","Unknown",_xlfn.IFS(E56<15,"Budget",E56<30,"Mid-range",TRUE(),"Luxury")) -> Luxury | U56: =IF(COUNTBLANK(D56:R56)>0,"Incomplete","Complete") -> Complete | V56: =IFERROR(RANK(D56,$D$2:$D$158),"") -> 17 | W56: =IFERROR(RANK(S56,$S$2:$S$158),"") -> 3
A57: Ford | B57: Ranger | C57: SUV/Truck/Van | D57: 220.65 | E57: 12.05 | F57: 2.5 | G57: 119 | H57: 117.5 | I57: 69.4 | J57: 200.7 | K57: 3.086 | L57: 20 | M57: 23 | N57: 7.85 | O57: 40922 | P57: =YEAR(O57) -> 2012 | Q57: =TEXT(O57,"mmm") -> Jan | R57: 47.389531 | S57: =IFERROR(D57*E57,"") -> 2658.8325 | T57: =IF(E57="","Unknown",_xlfn.IFS(E57<15,"Budget",E57<30,"Mid-range",TRUE(),"Luxury")) -> Budget | U57: =IF(COUNTBLANK(D57:R57)>0,"Incomplete","Complete") -> Complete | V57: =IFERROR(RANK(D57,$D$2:$D$158),"") -> 7 | W57: =IFERROR(RANK(S57,$S$2:$S$158),"") -> 12
A58: Ford | B58: F-Series | C58: SUV/Truck/Van | D58: 540.561 | E58: 26.935 | F58: 4.6 | G58: 220 | H58: 138.5 | I58: 79.1 | J58: 224.5 | K58: 4.241 | L58: 25.1 | M58: 18 | N58: 15.075 | O58: 41137 | P58: =YEAR(O58) -> 2012 | Q58: =TEXT(O58,"mmm") -> Aug | R58: 89.401935 | S58: =IFERROR(D58*E58,"") -> 14560.011 | T58: =IF(E58="","Unknown",_xlfn.IFS(E58<15,"Budget",E58<30,"Mid-range",TRUE(),"Luxury")) -> Mid-range | U58: =IF(COUNTBLANK(D58:R58)>0,"Incomplete","Complete") -> Complete | V58: =IFERROR(RANK(D58,$D$2:$D$158),"") -> 1 | W58: =IFERROR(RANK(S58,$S$2:$S$158),"") -> 1
A59: Honda | B59: Civic | C59: Passenger Car | D59: 199.685 | E59: 12.885 | F59: 1.6 | G59: 106 | H59: 103.2 | I59: 67.1 | J59: 175.1 | K59: 2.339 | L59: 11.9 | M59: 32 | N59: 9.85 | O59: 40837 | P59: =YEAR(O59) -> 2011 | Q59: =TEXT(O59,"mmm") -> Oct | R59: 42.879097 | S59: =IFERROR(D59*E59,"") -> 2572.9412 | T59: =IF(E59="","Unknown",_xlfn.IFS(E59<15,"Budget",E59<30,"Mid-range",TRUE(),"Luxury")) -> Budget | U59: =IF(COUNTBLANK(D59:R59)>0,"Incomplete","Complete") -> Complete | V59: =IFERROR(RANK(D59,$D$2:$D$158),"") -> 8 | W59: =IFERROR(RANK(S59,$S$2:$S$158),"") -> 14
A60: Honda | B60: Accord | C60: Passenger Car | D60: 230.902 | E60: 15.35 | F60: 2.3 | G60: 135 | H60: 106.9 | I60: 70.3 | J60: 188.8 | K60: 2.932 | L60: 17.1 | M60: 27 | N60: 13.21 | O60: 41049 | P60: =YEAR(O60) -> 2012 | Q60: =TEXT(O60,"mmm") -> May | R60: 54.269548 | S60: =IFERROR(D60*E60,"") -> 3544.3457 | T60: =IF(E60="","Unknown",_xlfn.IFS(E60<15,"Budget",E60<30,"Mid-range",TRUE(),"Luxury")) -> Mid-range | U60: =IF(COUNTBLANK(D60:R60)>0,"Incomplete","Complete") -> Complete | V60: =IFERROR(RANK(D60,$D$2:$D$158),"") -> 5 | W60: =IFERROR(RANK(S60,$S$2:$S$158),"") -> 9
A61: Honda | B61: CR-V | C61: SUV/Truck/Van | D61: 73.203 | E61: 20.55 | F61: 2 | G61: 146 | H61: 103.2 | I61: 68.9 | J61: 177.6 | K61: 3.219 | L61: 15.3 | M61: 24 | N61: 17.71 | O61: 40989 | P61: =YEAR(O61) -> 2012 | Q61: =TEXT(O61,"mmm") -> Mar | R61: 60.087967 | S61: =IFERROR(D61*E61,"") -> 1504.3217 | T61: =IF(E61="","Unknown",_xlfn.IFS(E61<15,"Budget",E61<30,"Mid-range",TRUE(),"Luxury")) -> Mid-range | U61: =IF(COUNTBLANK(D61:R61)>0,"Incomplete","Complete") -> Complete | V61: =IFERROR(RANK(D61,$D$2:$D$158),"") -> 36 | W61: =IFERROR(RANK(S61,$S$2:$S$158),"") -> 36
A62: Honda | B62: Passport | C62: SUV/Truck/Van | D62: 12.855 | E62: 26.6 | F62: 3.2 | G62: 205 | H62: 106.4 | I62: 70.4 | J62: 178.2 | K62: 3.857 | L62: 21.1 | M62: 19 | N62: 17.525 | O62: 41191 | P62: =YEAR(O62) -> 2012 | Q62: =TEXT(O62,"mmm") -> Oct | R62: 83.602501 | S62: =IFERROR(D62*E62,"") -> 341.943 | T62: =IF(E62="","Unknown",_xlfn.IFS(E62<15,"Budget",E62<30,"Mid-range",TRUE(),"Luxury")) -> Mid-range | U62: =IF(COUNTBLANK(D62:R62)>0,"Incomplete","Complete") -> Complete | V62: =IFERROR(RANK(D62,$D$2:$D$158),"") -> 121 | W62: =IFERROR(RANK(S62,$S$2:$S$158),"") -> 125
A63: Honda | B63: Odyssey | C63: SUV/Truck/Van | D63: 76.029 | E63: 26 | F63: 3.5 | G63: 210 | H63: 118.1 | I63: 75.6 | J63: 201.2 | K63: 4.288 | L63: 20 | M63: 23 | N63: 19.49 | O63: 40947 | P63: =YEAR(O63) -> 2012 | Q63: =TEXT(O63,"mmm") -> Feb | R63: 85.217691 | S63: =IFERROR(D63*E63,"") -> 1976.754 | T63: =IF(E63="","Unknown",_xlfn.IFS(E63<15,"Budget",E63<30,"Mid-range",TRUE(),"Luxury")) -> Mid-range | U63: =IF(COUNTBLANK(D63:R63)>0,"Incomplete","Complete") -> Complete | V63: =IFERROR(RANK(D63,$D$2:$D$158),"") -> 35 | W63: =IFERROR(RANK(S63,$S$2:$S$158),"") -> 26
A64: Hyundai | B64: Accent | C64: Passenger Car | D64: 41.184 | E64: 9.699 | F64: 1.5 | G64: 92 | H64: 96.1 | I64: 65.7 | J64: 166.7 | K64: 2.24 | L64: 11.9 | M64: 31 | N64: 5.86 | O64: 41162 | P64: =YEAR(O64) -> 2012 | Q64: =TEXT(O64,"mmm") -> Sep | R64: 36.672284 | S64: =IFERROR(D64*E64,"") -> 399.44362 | T64: =IF(E64="","Unknown",_xlfn.IFS(E64<15,"Budget",E64<30,"Mid-range",TRUE(),"Luxury")) -> Budget | U64: =IF(COUNTBLANK(D64:R64)>0,"Incomplete","Complete") -> Complete | V64: =IFERROR(RANK(D64,$D$2:$D$158),"") -> 62 | W64: =IFERROR(RANK(S64,$S$2:$S$158),"") -> 114
... A67: Infiniti | B67: I30 | C67: Passenger Car | D67: 23.713 | E67: 29.465 | F67: 3 | G67: 227 | H67: 108.3 | I67: 70.2 | J67: 193.7 | K67: 3.342 | L67: 18.5 | M67: 25 | N67: 19.69 | O67: 41014 | P67: =YEAR(O67) -> 2012 | Q67: =TEXT(O67,"mmm") -> Apr | R67: 92.436889 | S67: =IFERROR(D67*E67,"") -> 698.70355 | T67: =IF(E67="","Unknown",_xlfn.IFS(E67<15,"Budget",E67<30,"Mid-range",TRUE(),"Luxury")) -> Mid-range | U67: =IF(COUNTBLANK(D67:R67)>0,"Incomplete","Complete") -> Complete | V67: =IFERROR(RANK(D67,$D$2:$D$158),"") -> 94 | W67: =IFERROR(RANK(S67,$S$2:$S$158),"") -> 78
A68: Jaguar | B68: S-Type | C68: Passenger Car | D68: 15.467 | E68: 42.8 | F68: 3 | G68: 240 | H68: 114.5 | I68: 71.6 | J68: 191.3 | K68: 3.65 | L68: 18.4 | M68: 21 | O68: 41216 | P68: =YEAR(O68) -> 2012 | Q68: =TEXT(O68,"mmm") -> Nov | R68: 102.17898 | S68: =IFERROR(D68*E68,"") -> 661.9876 | T68: =IF(E68="","Unknown",_xlfn.IFS(E68<15,"Budget",E68<30,"Mid-range",TRUE(),"Luxury")) -> Luxury | U68: =IF(COUNTBLANK(D68:R68)>0,"Incomplete","Complete") -> Incomplete | V68: =IFERROR(RANK(D68,$D$2:$D$158),"") -> 113 | W68: =IFERROR(RANK(S68,$S$2:$S$158),"") -> 84
A69: Jeep | B69: Wrangler | C69: SUV/Truck/Van | D69: 55.557 | E69: 14.46 | F69: 2.5 | G69: 120 | H69: 93.4 | I69: 66.7 | J69: 152 | K69: 3.045 | L69: 19 | M69: 17 | N69: 13.475 | O69: 40972 | P69: =YEAR(O69) -> 2012 | Q69: =TEXT(O69,"mmm") -> Mar | R69: 48.672898 | S69: =IFERROR(D69*E69,"") -> 803.35422 | T69: =IF(E69="","Unknown",_xlfn.IFS(E69<15,"Budget",E69<30,"Mid-range",TRUE(),"Luxury")) -> Budget | U69: =IF(COUNTBLANK(D69:R69)>0,"Incomplete","Complete") -> Complete | V69: =IFERROR(RANK(D69,$D$2:$D$158),"") -> 48 | W69: =IFERROR(RANK(S69,$S$2:$S$158),"") -> 69
A70: Jeep | B70: Cherokee | C70: SUV/Truck/Van | D70: 80.556 | E70: 21.62 | F70: 4 | G70: 190 | H70: 101.4 | I70: 69.4 | J70: 167.5 | K70: 3.194 | L70: 20 | M70: 20 | N70: 13.775 | O70: 41187 | P70: =YEAR(O70) -> 2012 | Q70: =TEXT(O70,"mmm") -> Oct | R70: 76.58444 | S70: =IFERROR(D70*E70,"") -> 1741.6207 | T70: =IF(E70="","Unknown",_xlfn.IFS(E70<15,"Budget",E70<30,"Mid-range",TRUE(),"Luxury")) -> Mid-range | U70: =IF(COUNTBLANK(D70:R70)>0,"Incomplete","Complete") -> Complete | V70: =IFERROR(RANK(D70,$D$2:$D$158),"") -> 31 | W70: =IFERROR(RANK(S70,$S$2:$S$158),"") -> 33
A71: Jeep | B71: Grand Cherokee | C71: SUV/Truck/Van | D71: 157.04 | E71: 26.895 | F71: 4 | G71: 195 | H71: 105.9 | I71: 72.3 | J71: 181.5 | K71: 3.88 | L71: 20.5 | M71: 19 | N71: 18.81 | O71: 40887 | P71: =YEAR(O71) -> 2011 | Q71: =TEXT(O71,"mmm") -> Dec | R71: 80.387779 | S71: =IFERROR(D71*E71,"") -> 4223.5908 | T71: =IF(E71="","Unknown",_xlfn.IFS(E71<15,"Budget",E71<30,"Mid-range",TRUE(),"Luxury")) -> Mid-range | U71: =IF(COUNTBLANK(D71:R71)>0,"Incomplete","Complete") -> Complete | V71: =IFERROR(RANK(D71,$D$2:$D$158),"") -> 11 | W71: =IFERROR(RANK(S71,$S$2:$S$158),"") -> 7
A72: Lexus | B72: ES300 | C72: Passenger Car | D72: 24.072 | E72: 31.505 | F72: 3 | G72: 210 | H72: 105.1 | I72: 70.5 | J72: 190.2 | K72: 3.373 | L72: 18.5 | M72: 23 | N72: 26.975 | O72: 41099 | P72: =YEAR(O72) -> 2012 | Q72: =TEXT(O72,"mmm") -> Jul | R72: 87.211001 | S72: =IFERROR(D72*E72,"") -> 758.38836 | T72: =IF(E72="","Unknown",_xlfn.IFS(E72<15,"Budget",E72<30,"Mid-range",TRUE(),"Luxury")) -> Luxury | U72: =IF(COUNTBLANK(D72:R72)>0,"Incomplete","Complete") -> Complete | V72: =IFERROR(RANK(D72,$D$2:$D$158),"") -> 93 | W72: =IFERROR(RANK(S72,$S$2:$S$158),"") -> 74
A73: Lexus | B73: GS300 | C73: Passenger Car | D73: 12.698 | E73: 37.805 | F73: 3 | G73: 225 | H73: 110.2 | I73: 70.9 | J73: 189.2 | K73: 3.638 | L73: 19.8 | M73: 23 | N73: 32.075 | O73: 41039 | P73: =YEAR(O73) -> 2012 | Q73: =TEXT(O73,"mmm") -> May | R73: 94.946698 | S73: =IFERROR(D73*E73,"") -> 480.04789 | T73: =IF(E73="","Unknown",_xlfn.IFS(E73<15,"Budget",E73<30,"Mid-range",TRUE(),"Luxury")) -> Luxury | U73: =IF(COUNTBLANK(D73:R73)>0,"Incomplete","Complete") -> Complete | V73: =IFERROR(RANK(D73,$D$2:$D$158),"") -> 122 | W73: =IFERROR(RANK(S73,$S$2:$S$158),"") -> 104
A74: Lexus | B74: GS400 | C74: Passenger Car | D74: 3.334 | E74: 46.305 | F74: 4 | G74: 300 | H74: 110.2 | I74: 70.9 | J74: 189.2 | K74: 3.693 | L74: 19.8 | M74: 21 | O74: 41241 | P74: =YEAR(O74) -> 2012 | Q74: =TEXT(O74,"mmm") -> Nov | R74: 125.01336 | S74: =IFERROR(D74*E74,"") -> 154.38087 | T74: =IF(E74="","Unknown",_xlfn.IFS(E74<15,"Budget",E74<30,"Mid-range",TRUE(),"Luxury")) -> Luxury | U74: =IF(COUNTBLANK(D74:R74)>0,"Incomplete","Complete") -> Incomplete | V74: =IFERROR(RANK(D74,$D$2:$D$158),"") -> 147 | W74: =IFERROR(RANK(S74,$S$2:$S$158),"") -> 139
A75: Lexus | B75: LS400 | C75: Passenger Car | D75: 6.375 | E75: 54.005 | F75: 4 | G75: 290 | H75: 112.2 | I75: 72 | J75: 196.7 | K75: 3.89 | L75: 22.5 | M75: 22 | N75: 40.375 | O75: 40997 | P75: =YEAR(O75) -> 2012 | Q75: =TEXT(O75,"mmm") -> Mar | R75: 124.44672 | S75: =IFERROR(D75*E75,"") -> 344.28188 | T75: =IF(E75="","Unknown",_xlfn.IFS(E75<15,"Budget",E75<30,"Mid-range",TRUE(),"Luxury")) -> Luxury | U75: =IF(COUNTBLANK(D75:R75)>0,"Incomplete","Complete") -> Complete | V75: =IFERROR(RANK(D75,$D$2:$D$158),"") -> 139 | W75: =IFERROR(RANK(S75,$S$2:$S$158),"") -> 124
A76: Lexus | B76: LX470 | C76: SUV/Truck/Van | D76: 9.126 | E76: 60.105 | F76: 4.7 | G76: 230 | H76: 112.2 | I76: 76.4 | J76: 192.5 | K76: 5.401 | L76: 25.4 | M76: 15 | O76: 41212 | P76: =YEAR(O76) -> 2012 | Q76: =TEXT(O76,"mmm") -> Oct | R76: 105.76046 | S76: =IFERROR(D76*E76,"") -> 548.51823 | T76: =IF(E76="","Unknown",_xlfn.IFS(E76<15,"Budget",E76<30,"Mid-range",TRUE(),"Luxury")) -> Luxury | U76: =IF(COUNTBLANK(D76:R76)>0,"Incomplete","Complete") -> Incomplete | V76: =IFERROR(RANK(D76,$D$2:$D$158),"") -> 132 | W76: =IFERROR(RANK(S76,$S$2:$S$158),"") -> 94
A77: Lexus | B77: RX300 | C77: SUV/Truck/Van | D77: 51.238 | E77: 34.605 | F77: 3 | G77: 220 | H77: 103 | I77: 71.5 | J77: 180.1 | K77: 3.9 | L77: 17.2 | M77: 21 | O77: 40912 | P77: =YEAR(O77) -> 2012 | Q77: =TEXT(O77,"mmm") -> Jan | R77: 91.943802 | S77: =IFERROR(D77*E77,"") -> 1773.091 | T77: =IF(E77="","Unknown",_xlfn.IFS(E77<15,"Budget",E77<30,"Mid-range",TRUE(),"Luxury")) -> Luxury | U77: =IF(COUNTBLANK(D77:R77)>0,"Incomplete","Complete") -> Incomplete | V77: =IFERROR(RANK(D77,$D$2:$D$158),"") -> 52 | W77: =IFERROR(RANK(S77,$S$2:$S$158),"") -> 32
A78: Lincoln | B78: Continental | C78: Passenger Car | D78: 13.798 | E78: 39.08 | F78: 4.6 | G78: 275 | H78: 109 | I78: 73.6 | J78: 208.5 | K78: 3.868 | L78: 20 | M78: 22 | N78: 20.525 | O78: 41124 | P78: =YEAR(O78) -> 2012 | Q78: =TEXT(O78,"mmm") -> Aug | R78: 113.54021 | S78: =IFERROR(D78*E78,"") -> 539.22584 | T78: =IF(E78="","Unknown",_xlfn.IFS(E78<15,"Budget",E78<30,"Mid-range",TRUE(),"Luxury")) -> Luxury | U78: =IF(COUNTBLANK(D78:R78)>0,"Incomplete","Complete") -> Complete | V78: =IFERROR(RANK(D78,$D$2:$D$158),"") -> 119 | W78: =IFERROR(RANK(S78,$S$2:$S$158),"") -> 95
A79: Lincoln | B79: Town Car | C79: Passenger Car | D79: 48.911 | E79: 43.33 | F79: 4.6 | G79: 215 | H79: 117.7 | I79: 78.2 | J79: 215.3 | K79: 4.121 | L79: 19 | M79: 21 | N79: 21.725 | O79: 41064 | P79: =YEAR(O79) -> 2012 | Q79: =TEXT(O79,"mmm") -> Jun | R79: 93.957917 | S79: =IFERROR(D79*E79,"") -> 2119.3136 | T79: =IF(E79="","Unknown",_xlfn.IFS(E79<15,"Budget",E79<30,"Mid-range",TRUE(),"Luxury")) -> Luxury | U79: =IF(COUNTBLANK(D79:R79)>0,"Incomplete","Complete") -> Complete | V79: =IFERROR(RANK(D79,$D$2:$D$158),"") -> 56 | W79: =IFERROR(RANK(S79,$S$2:$S$158),"") -> 20
A80: Lincoln | B80: Navigator | C80: SUV/Truck/Van | D80: 22.925 | E80: 42.66 | F80: 5.4 | G80: 300 | H80: 119 | I80: 79.9 | J80: 204.8 | K80: 5.393 | L80: 30 | M80: 15 | O80: 41266 | P80: =YEAR(O80) -> 2012 | Q80: =TEXT(O80,"mmm") -> Dec | R80: 123.97205 | S80: =IFERROR(D80*E80,"") -> 977.9805 | T80: =IF(E80="","Unknown",_xlfn.IFS(E80<15,"Budget",E80<30,"Mid-range",TRUE(),"Luxury")) -> Luxury | U80: =IF(COUNTBLANK(D80:R80)>0,"Incomplete","Complete") -> Incomplete | V80: =IFERROR(RANK(D80,$D$2:$D$158),"") -> 95 | W80: =IFERROR(RANK(S80,$S$2:$S$158),"") -> 55
A81: Mitsubishi | B81: Mirage | C81: Passenger Car | D81: 26.232 | E81: 13.987 | F81: 1.8 | G81: 113 | H81: 98.4 | I81: 66.5 | J81: 173.6 | K81: 2.25 | L81: 13.2 | M81: 30 | N81: 8.325 | O81: 41022 | P81: =YEAR(O81) -> 2012 | Q81: =TEXT(O81,"mmm") -> Apr | R81: 45.832181 | S81: =IFERROR(D81*E81,"") -> 366.90698 | T81: =IF(E81="","Unknown",_xlfn.IFS(E81<15,"Budget",E81<30,"Mid-range",TRUE(),"Luxury")) -> Budget | U81: =IF(COUNTBLANK(D81:R81)>0,"Incomplete","Complete") -> Complete | V81: =IFERROR(RANK(D81,$D$2:$D$158),"") -> 87 | W81: =IFERROR(RANK(S81,$S$2:$S$158),"") -> 118
A82: Mitsubishi | B82: Eclipse | C82: Passenger Car | D82: 42.541 | E82: 19.047 | F82: 2.4 | G82: 154 | H82: 100.8 | I82: 68.9 | J82: 175.4 | K82: 2.91 | L82: 15.9 | M82: 24 | N82: 10.395 | O82: 41237 | P82: =YEAR(O82) -> 2012 | Q82: =TEXT(O82,"mmm") -> Nov | R82: 62.441962 | S82: =IFERROR(D82*E82,"") -> 810.27843 | T82: =IF(E82="","Unknown",_xlfn.IFS(E82<15,"Budget",E82<30,"Mid-range",TRUE(),"Luxury")) -> Mid-range | U82: =IF(COUNTBLANK(D82:R82)>0,"Incomplete","Complete") -> Complete | V82: =IFERROR(RANK(D82,$D$2:$D$158),"") -> 61 | W82: =IFERROR(RANK(S82,$S$2:$S$158),"") -> 68
A83: Mitsubishi | B83: Galant | C83: Passenger Car | D83: 55.616 | E83: 17.357 | F83: 2.4 | G83: 145 | H83: 103.7 | I83: 68.5 | J83: 187.8 | K83: 2.945 | L83: 16.3 | M83: 25 | N83: 10.595 | O83: 40937 | P83: =YEAR(O83) -> 2012 | Q83: =TEXT(O83,"mmm") -> Jan | R83: 58.606773 | S83: =IFERROR(D83*E83,"") -> 965.32691 | T83: =IF(E83="","Unknown",_xlfn.IFS(E83<15,"Budget",E83<30,"Mid-range",TRUE(),"Luxury")) -> Mid-range | U83: =IF(COUNTBLANK(D83:R83)>0,"Incomplete","Complete") -> Complete | V83: =IFERROR(RANK(D83,$D$2:$D$158),"") -> 47 | W83: =IFERROR(RANK(S83,$S$2:$S$158),"") -> 57
A84: Mitsubishi | B84: Diamante | C84: Passenger Car | D84: 5.711 | E84: 24.997 | F84: 3.5 | G84: 210 | H84: 107.1 | I84: 70.3 | J84: 194.1 | K84: 3.443 | L84: 19 | M84: 22 | N84: 16.575 | O84: 41149 | P84: =YEAR(O84) -> 2012 | Q84: =TEXT(O84,"mmm") -> Aug | R84: 84.830779 | S84: =IFERROR(D84*E84,"") -> 142.75787 | T84: =IF(E84="","Unknown",_xlfn.IFS(E84<15,"Budget",E84<30,"Mid-range",TRUE(),"Luxury")) -> Mid-range | U84: =IF(COUNTBLANK(D84:R84)>0,"Incomplete","Complete") -> Complete | V84: =IFERROR(RANK(D84,$D$2:$D$158),"") -> 140 | W84: =IFERROR(RANK(S84,$S$2:$S$158),"") -> 141
A85: Mitsubishi | B85: 3000GT | C85: Passenger Car | D85: 0.11 | E85: 25.45 | F85: 3 | G85: 161 | H85: 97.2 | I85: 72.4 | J85: 180.3 | K85: 3.131 | L85: 19.8 | M85: 21 | N85: 20.94 | O85: 41089 | P85: =YEAR(O85) -> 2012 | Q85: =TEXT(O85,"mmm") -> Jun | R85: 67.544155 | S85: =IFERROR(D85*E85,"") -> 2.7995 | T85: =IF(E85="","Unknown",_xlfn.IFS(E85<15,"Budget",E85<30,"Mid-range",TRUE(),"Luxury")) -> Mid-range | U85: =IF(COUNTBLANK(D85:R85)>0,"Incomplete","Complete") -> Complete | V85: =IFERROR(RANK(D85,$D$2:$D$158),"") -> 157 | W85: =IFERROR(RANK(S85,$S$2:$S$158),"") -> 155
A86: Mitsubishi | B86: Montero | C86: SUV/Truck/Van | D86: 11.337 | E86: 31.807 | F86: 3.5 | G86: 200 | H86: 107.3 | I86: 69.9 | J86: 186.6 | K86: 4.52 | L86: 24.3 | M86: 18 | N86: 19.125 | O86: 40925 | P86: =YEAR(O86) -> 2012 | Q86: =TEXT(O86,"mmm") -> Jan | R86: 83.920815 | S86: =IFERROR(D86*E86,"") -> 360.59596 | T86: =IF(E86="","Unknown",_xlfn.IFS(E86<15,"Budget",E86<30,"Mid-range",TRUE(),"Luxury")) -> Luxury | U86: =IF(COUNTBLANK(D86:R86)>0,"Incomplete","Complete") -> Complete | V86: =IFERROR(RANK(D86,$D$2:$D$158),"") -> 125 | W86: =IFERROR(RANK(S86,$S$2:$S$158),"") -> 121
A87: Mitsubishi | B87: Montero Sport | C87: SUV/Truck/Van | D87: 39.348 | E87: 22.527 | F87: 3 | G87: 173 | H87: 107.3 | I87: 66.7 | J87: 178.3 | K87: 3.51 | L87: 19.5 | M87: 20 | N87: 13.88 | O87: 41047 | P87: =YEAR(O87) -> 2012 | Q87: =TEXT(O87,"mmm") -> May | R87: 70.660942 | S87: =IFERROR(D87*E87,"") -> 886.3924 | T87: =IF(E87="","Unknown",_xlfn.IFS(E87<15,"Budget",E87<30,"Mid-range",TRUE(),"Luxury")) -> Mid-range | U87: =IF(COUNTBLANK(D87:R87)>0,"Incomplete","Complete") -> Complete | V87: =IFERROR(RANK(D87,$D$2:$D$158),"") -> 66 | W87: =IFERROR(RANK(S87,$S$2:$S$158),"") -> 62
A88: Mercury | B88: Mystique | C88: Passenger Car | D88: 14.351 | E88: 16.24 | F88: 2 | G88: 125 | H88: 106.5 | I88: 69.1 | J88: 184.8 | K88: 2.769 | L88: 15 | M88: 28 | N88: 8.8 | O88: 41262 | P88: =YEAR(O88) -> 2012 | Q88: =TEXT(O88,"mmm") -> Dec | R88: 50.997748 | S88: =IFERROR(D88*E88,"") -> 233.06024 | T88: =IF(E88="","Unknown",_xlfn.IFS(E88<15,"Budget",E88<30,"Mid-range",TRUE(),"Luxury")) -> Mid-range | U88: =IF(COUNTBLANK(D88:R88)>0,"Incomplete","Complete") -> Complete | V88: =IFERROR(RANK(D88,$D$2:$D$158),"") -> 117 | W88: =IFERROR(RANK(S88,$S$2:$S$158),"") -> 133
A89: Mercury | B89: Cougar | C89: Passenger Car | D89: 26.529 | E89: 16.54 | F89: 2 | G89: 125 | H89: 106.4 | I89: 69.6 | J89: 185 | K89: 2.892 | L89: 16 | M89: 30 | N89: 13.89 | O89: 40962 | P89: =YEAR(O89) -> 2012 | Q89: =TEXT(O89,"mmm") -> Feb | R89: 51.113474 | S89: =IFERROR(D89*E89,"") -> 438.78966 | T89: =IF(E89="","Unknown",_xlfn.IFS(E89<15,"Budget",E89<30,"Mid-range",TRUE(),"Luxury")) -> Mid-range | U89: =IF(COUNTBLANK(D89:R89)>0,"Incomplete","Complete") -> Complete | V89: =IFERROR(RANK(D89,$D$2:$D$158),"") -> 85 | W89: =IFERROR(RANK(S89,$S$2:$S$158),"") -> 110
A90: Mercury | B90: Sable | C90: Passenger Car | D90: 67.956 | E90: 19.035 | F90: 3 | G90: 153 | H90: 108.5 | I90: 73 | J90: 199.7 | K90: 3.379 | L90: 16 | M90: 24 | N90: 11.03 | O90: 41174 | P90: =YEAR(O90) -> 2012 | Q90: =TEXT(O90,"mmm") -> Sep | R90: 62.239967 | S90: =IFERROR(D90*E90,"") -> 1293.5425 | T90: =IF(E90="","Unknown",_xlfn.IFS(E90<15,"Budget",E90<30,"Mid-range",TRUE(),"Luxury")) -> Mid-range | U90: =IF(COUNTBLANK(D90:R90)>0,"Incomplete","Complete") -> Complete | V90: =IFERROR(RANK(D90,$D$2:$D$158),"") -> 40 | W90: =IFERROR(RANK(S90,$S$2:$S$158),"") -> 43
A91: Mercury | B91: Grand Marquis | C91: Passenger Car | D91: 81.174 | E91: 22.605 | F91: 4.6 | G91: 200 | H91: 114.7 | I91: 78.2 | J91: 212 | K91: 3.958 | L91: 19 | M91: 21 | N91: 14.875 | O91: 41114 | P91: =YEAR(O91) -> 2012 | Q91: =TEXT(O91,"mmm") -> Jul | R91: 80.657696 | S91: =IFERROR(D91*E91,"") -> 1834.9383 | T91: =IF(E91="","Unknown",_xlfn.IFS(E91<15,"Budget",E91<30,"Mid-range",TRUE(),"Luxury")) -> Mid-range | U91: =IF(COUNTBLANK(D91:R91)>0,"Incomplete","Complete") -> Complete | V91: =IFERROR(RANK(D91,$D$2:$D$158),"") -> 29 | W91: =IFERROR(RANK(S91,$S$2:$S$158),"") -> 30
A92: Mercury | B92: Mountaineer | C92: SUV/Truck/Van | D92: 27.609 | E92: 27.56 | F92: 4 | G92: 210 | H92: 111.6 | I92: 70.2 | J92: 190.1 | K92: 3.876 | L92: 21 | M92: 18 | N92: 20.43 | O92: 39491 | P92: =YEAR(O92) -> 2008 | Q92: =TEXT(O92,"mmm") -> Feb | R92: 85.949744 | S92: =IFERROR(D92*E92,"") -> 760.90404 | T92: =IF(E92="","Unknown",_xlfn.IFS(E92<15,"Budget",E92<30,"Mid-range",TRUE(),"Luxury")) -> Mid-range | U92: =IF(COUNTBLANK(D92:R92)>0,"Incomplete","Complete") -> Complete | V92: =IFERROR(RANK(D92,$D$2:$D$158),"") -> 82 | W92: =IFERROR(RANK(S92,$S$2:$S$158),"") -> 73
... A97: Mercedes-Benz | B97: SL-Class | C97: Passenger Car | D97: 3.311 | E97: 82.6 | F97: 5 | G97: 302 | H97: 99 | I97: 71.3 | J97: 177.1 | K97: 4.125 | L97: 21.1 | M97: 20 | N97: 58.6 | O97: 40619 | P97: =YEAR(O97) -> 2011 | Q97: =TEXT(O97,"mmm") -> Mar | R97: 139.98229 | S97: =IFERROR(D97*E97,"") -> 273.4886 | T97: =IF(E97="","Unknown",_xlfn.IFS(E97<15,"Budget",E97<30,"Mid-range",TRUE(),"Luxury")) -> Luxury | U97: =IF(COUNTBLANK(D97:R97)>0,"Incomplete","Complete") -> Complete | V97: =IFERROR(RANK(D97,$D$2:$D$158),"") -> 148 | W97: =IFERROR(RANK(S97,$S$2:$S$158),"") -> 131
A98: Mercedes-Benz | B98: SLK | C98: Passenger Car | D98: 7.998 | E98: 38.9 | F98: 2.3 | G98: 190 | H98: 94.5 | I98: 67.5 | J98: 157.9 | K98: 3.055 | L98: 15.9 | M98: 26 | O98: 40559 | P98: =YEAR(O98) -> 2011 | Q98: =TEXT(O98,"mmm") -> Jan | R98: 82.807362 | S98: =IFERROR(D98*E98,"") -> 311.1222 | T98: =IF(E98="","Unknown",_xlfn.IFS(E98<15,"Budget",E98<30,"Mid-range",TRUE(),"Luxury")) -> Luxury | U98: =IF(COUNTBLANK(D98:R98)>0,"Incomplete","Complete") -> Incomplete | V98: =IFERROR(RANK(D98,$D$2:$D$158),"") -> 136 | W98: =IFERROR(RANK(S98,$S$2:$S$158),"") -> 127
A99: Mercedes-Benz | B99: SLK230 | C99: Passenger Car | D99: 1.526 | E99: 41 | F99: 2.3 | G99: 185 | H99: 94.5 | I99: 67.5 | J99: 157.3 | K99: 2.975 | L99: 14 | M99: 27 | O99: 40761 | P99: =YEAR(O99) -> 2011 | Q99: =TEXT(O99,"mmm") -> Aug | R99: 81.848969 | S99: =IFERROR(D99*E99,"") -> 62.566 | T99: =IF(E99="","Unknown",_xlfn.IFS(E99<15,"Budget",E99<30,"Mid-range",TRUE(),"Luxury")) -> Luxury | U99: =IF(COUNTBLANK(D99:R99)>0,"Incomplete","Complete") -> Incomplete | V99: =IFERROR(RANK(D99,$D$2:$D$158),"") -> 151 | W99: =IFERROR(RANK(S99,$S$2:$S$158),"") -> 153
A100: Mercedes-Benz | B100: CLK Coupe | C100: Passenger Car | D100: 11.592 | E100: 41.6 | F100: 3.2 | G100: 215 | H100: 105.9 | I100: 67.8 | J100: 180.3 | K100: 3.213 | L100: 16.4 | M100: 26 | O100: 40732 | P100: =YEAR(O100) -> 2011 | Q100: =TEXT(O100,"mmm") -> Jul | R100: 92.925792 | S100: =IFERROR(D100*E100,"") -> 482.2272 | T100: =IF(E100="","Unknown",_xlfn.IFS(E100<15,"Budget",E100<30,"Mid-range",TRUE(),"Luxury")) -> Luxury | U100: =IF(COUNTBLANK(D100:R100)>0,"Incomplete","Complete") -> Incomplete | V100: =IFERROR(RANK(D100,$D$2:$D$158),"") -> 124 | W100: =IFERROR(RANK(S100,$S$2:$S$158),"") -> 103
A101: Mercedes-Benz | B101: CL500 | C101: Passenger Car | D101: 0.954 | E101: 85.5 | F101: 5 | G101: 302 | H101: 113.6 | I101: 73.1 | J101: 196.6 | K101: 4.115 | L101: 23.2 | M101: 20 | O101: 40644 | P101: =YEAR(O101) -> 2011 | Q101: =TEXT(O101,"mmm") -> Apr | R101: 141.10098 | S101: =IFERROR(D101*E101,"") -> 81.567 | T101: =IF(E101="","Unknown",_xlfn.IFS(E101<15,"Budget",E101<30,"Mid-range",TRUE(),"Luxury")) -> Luxury | U101: =IF(COUNTBLANK(D101:R101)>0,"Incomplete","Complete") -> Incomplete | V101: =IFERROR(RANK(D101,$D$2:$D$158),"") -> 155 | W101: =IFERROR(RANK(S101,$S$2:$S$158),"") -> 149
A102: Mercedes-Benz | B102: M-Class | C102: SUV/Truck/Van | D102: 28.976 | E102: 35.3 | F102: 3.2 | G102: 215 | H102: 111 | I102: 72.2 | J102: 180.6 | K102: 4.387 | L102: 19 | M102: 20 | O102: 40584 | P102: =YEAR(O102) -> 2011 | Q102: =TEXT(O102,"mmm") -> Feb | R102: 90.495532 | S102: =IFERROR(D102*E102,"") -> 1022.8528 | T102: =IF(E102="","Unknown",_xlfn.IFS(E102<15,"Budget",E102<30,"Mid-range",TRUE(),"Luxury")) -> Luxury | U102: =IF(COUNTBLANK(D102:R102)>0,"Incomplete","Complete") -> Incomplete | V102: =IFERROR(RANK(D102,$D$2:$D$158),"") -> 80 | W102: =IFERROR(RANK(S102,$S$2:$S$158),"") -> 52
A103: Nissan | B103: Sentra | C103: Passenger Car | D103: 42.643 | E103: 13.499 | F103: 1.8 | G103: 126 | H103: 99.8 | I103: 67.3 | J103: 177.5 | K103: 2.593 | L103: 13.2 | M103: 30 | N103: 8.45 | O103: 40786 | P103: =YEAR(O103) -> 2011 | Q103: =TEXT(O103,"mmm") -> Aug | R103: 50.241978 | S103: =IFERROR(D103*E103,"") -> 575.63786 | T103: =IF(E103="","Unknown",_xlfn.IFS(E103<15,"Budget",E103<30,"Mid-range",TRUE(),"Luxury")) -> Budget | U103: =IF(COUNTBLANK(D103:R103)>0,"Incomplete","Complete") -> Complete | V103: =IFERROR(RANK(D103,$D$2:$D$158),"") -> 58 | W103: =IFERROR(RANK(S103,$S$2:$S$158),"") -> 92
A104: Nissan | B104: Altima | C104: Passenger Car | D104: 88.094 | E104: 20.39 | F104: 2.4 | G104: 155 | H104: 103.1 | I104: 69.1 | J104: 183.5 | K104: 3.012 | L104: 15.9 | M104: 25 | N104: 11.295 | O104: 40757 | P104: =YEAR(O104) -> 2011 | Q104: =TEXT(O104,"mmm") -> Aug | R104: 63.313728 | S104: =IFERROR(D104*E104,"") -> 1796.2367 | T104: =IF(E104="","Unknown",_xlfn.IFS(E104<15,"Budget",E104<30,"Mid-range",TRUE(),"Luxury")) -> Mid-range | U104: =IF(COUNTBLANK(D104:R104)>0,"Incomplete","Complete") -> Complete | V104: =IFERROR(RANK(D104,$D$2:$D$158),"") -> 24 | W104: =IFERROR(RANK(S104,$S$2:$S$158),"") -> 31
A105: Nissan | B105: Maxima | C105: Passenger Car | D105: 79.853 | E105: 26.249 | F105: 3 | G105: 222 | H105: 108.3 | I105: 70.3 | J105: 190.5 | K105: 3.294 | L105: 18.5 | M105: 25 | N105: 15.125 | O105: 40669 | P105: =YEAR(O105) -> 2011 | Q105: =TEXT(O105,"mmm") -> May | R105: 89.42782 | S105: =IFERROR(D105*E105,"") -> 2096.0614 | T105: =IF(E105="","Unknown",_xlfn.IFS(E105<15,"Budget",E105<30,"Mid-range",TRUE(),"Luxury")) -> Mid-range | U105: =IF(COUNTBLANK(D105:R105)>0,"Incomplete","Complete") -> Complete | V105: =IFERROR(RANK(D105,$D$2:$D$158),"") -> 33 | W105: =IFERROR(RANK(S105,$S$2:$S$158),"") -> 21
A106: Nissan | B106: Quest | C106: SUV/Truck/Van | D106: 27.308 | E106: 26.399 | F106: 3.3 | G106: 170 | H106: 112.2 | I106: 74.9 | J106: 194.8 | K106: 3.991 | L106: 20 | M106: 21 | N106: 15.38 | O106: 40609 | P106: =YEAR(O106) -> 2011 | Q106: =TEXT(O106,"mmm") -> Mar | R106: 71.171664 | S106: =IFERROR(D106*E106,"") -> 720.90389 | T106: =IF(E106="","Unknown",_xlfn.IFS(E106<15,"Budget",E106<30,"Mid-range",TRUE(),"Luxury")) -> Mid-range | U106: =IF(COUNTBLANK(D106:R106)>0,"Incomplete","Complete") -> Complete | V106: =IFERROR(RANK(D106,$D$2:$D$158),"") -> 84 | W106: =IFERROR(RANK(S106,$S$2:$S$158),"") -> 76
...

Sheet Dashboard
B2: CAR SALES ANALYSIS DASHBOARD
B5: Filter by Brand: | D5: All Brands
B7: Total Cars Sold (units) | D7: Total Sales Revenue ($M) | F7: Average Car Price ($000) | H7: Highest Car Price ($000) | J7: Avg Units Sold per Model (000s)* | L7: Total Brands
B8: =IF($D$5="All Brands",SUM('Cleaned Data'!$D:$D),SUMIFS('Cleaned Data'!$D:$D,'Cleaned Data'!$A:$A,$D$5))*1000 -> 8320698 | D8: =IF($D$5="All Brands",SUM('Cleaned Data'!$S:$S),SUMIFS('Cleaned Data'!$S:$S,'Cleaned Data'!$A:$A,$D$5)) -> 179992.3 | F8: =IF($D$5="All Brands",AVERAGE('Cleaned Data'!$E:$E),AVERAGEIFS('Cleaned Data'!$E:$E,'Cleaned Data'!$A:$A,$D$5)) -> 27.390755 | H8: =IF($D$5="All Brands",MAX('Cleaned Data'!$E:$E),_xlfn.MAXIFS('Cleaned Data'!$E:$E,'Cleaned Data'!$A:$A,$D$5)) -> 85.5 | J8: =IF($D$5="All Brands",AVERAGE('Cleaned Data'!$D:$D),AVERAGEIFS('Cleaned Data'!$D:$D,'Cleaned Data'!$A:$A,$D$5)) -> 52.998076 | L8: =IF($D$5="All Brands",SUMPRODUCT(1/COUNTIF('Cleaned Data'!$A$2:$A$158,'Cleaned Data'!$A$2:$A$158)),1) -> 30

Sheet Analysis
B2: Analysis — Pivot-Style Summary Tables
B4: Brand Summary
B5: Brand | C5: Total Units Sold | D5: Total Revenue ($M) | E5: Avg Price ($) | F5: Number of Models | G5: Avg Resale Value ($) | H5: Revenue Rank
B6: Acura | C6: =SUMIFS('Cleaned Data'!$D:$D,'Cleaned Data'!$A:$A,$B6) -> 79.005 | D6: =SUMIFS('Cleaned Data'!$S:$S,'Cleaned Data'!$A:$A,$B6) -> 1842.9601 | E6: =IFERROR(AVERAGEIFS('Cleaned Data'!$E:$E,'Cleaned Data'!$A:$A,$B6),0) -> 30.633333 | F6: =COUNTIFS('Cleaned Data'!$A:$A,$B6) -> 4 | G6: =IFERROR(AVERAGEIFS('Cleaned Data'!$N:$N,'Cleaned Data'!$A:$A,$B6),0) -> 21.04625 | H6: =RANK(D6,$D$6:$D$35) -> 21
B7: Audi | C7: =SUMIFS('Cleaned Data'!$D:$D,'Cleaned Data'!$A:$A,$B7) -> 40.557 | D7: =SUMIFS('Cleaned Data'!$S:$S,'Cleaned Data'!$A:$A,$B7) -> 1212.465 | E7: =IFERROR(AVERAGEIFS('Cleaned Data'!$E:$E,'Cleaned Data'!$A:$A,$B7),0) -> 39.98 | F7: =COUNTIFS('Cleaned Data'!$A:$A,$B7) -> 3 | G7: =IFERROR(AVERAGEIFS('Cleaned Data'!$N:$N,'Cleaned Data'!$A:$A,$B7),0) -> 28.27 | H7: =RANK(D7,$D$6:$D$35) -> 25
B8: BMW | C8: =SUMIFS('Cleaned Data'!$D:$D,'Cleaned Data'!$A:$A,$B8) -> 46.505 | D8: =SUMIFS('Cleaned Data'!$S:$S,'Cleaned Data'!$A:$A,$B8) -> 1523.0872 | E8: =IFERROR(AVERAGEIFS('Cleaned Data'!$E:$E,'Cleaned Data'!$A:$A,$B8),0) -> 33.096667 | F8: =COUNTIFS('Cleaned Data'!$A:$A,$B8) -> 3 | G8: =IFERROR(AVERAGEIFS('Cleaned Data'!$N:$N,'Cleaned Data'!$A:$A,$B8),0) -> 32.4 | H8: =RANK(D8,$D$6:$D$35) -> 24
B9: Buick | C9: =SUMIFS('Cleaned Data'!$D:$D,'Cleaned Data'!$A:$A,$B9) -> 242.019 | D9: =SUMIFS('Cleaned Data'!$S:$S,'Cleaned Data'!$A:$A,$B9) -> 6219.4866 | E9: =IFERROR(AVERAGEIFS('Cleaned Data'!$E:$E,'Cleaned Data'!$A:$A,$B9),0) -> 26.78125 | F9: =COUNTIFS('Cleaned Data'!$A:$A,$B9) -> 4 | G9: =IFERROR(AVERAGEIFS('Cleaned Data'!$N:$N,'Cleaned Data'!$A:$A,$B9),0) -> 14.94125 | H9: =RANK(D9,$D$6:$D$35) -> 9
B10: Cadillac | C10: =SUMIFS('Cleaned Data'!$D:$D,'Cleaned Data'!$A:$A,$B10) -> 112.178 | D10: =SUMIFS('Cleaned Data'!$S:$S,'Cleaned Data'!$A:$A,$B10) -> 4541.0673 | E10: =IFERROR(AVERAGEIFS('Cleaned Data'!$E:$E,'Cleaned Data'!$A:$A,$B10),0) -> 40.254 | F10: =COUNTIFS('Cleaned Data'!$A:$A,$B10) -> 5 | G10: =IFERROR(AVERAGEIFS('Cleaned Data'!$N:$N,'Cleaned Data'!$A:$A,$B10),0) -> 23.39375 | H10: =RANK(D10,$D$6:$D$35) -> 12
B11: Chevrolet | C11: =SUMIFS('Cleaned Data'!$D:$D,'Cleaned Data'!$A:$A,$B11) -> 554.365 | D11: =SUMIFS('Cleaned Data'!$S:$S,'Cleaned Data'!$A:$A,$B11) -> 9610.6533 | E11: =IFERROR(AVERAGEIFS('Cleaned Data'!$E:$E,'Cleaned Data'!$A:$A,$B11),0) -> 20.022778 | F11: =COUNTIFS('Cleaned Data'!$A:$A,$B11) -> 9 | G11: =IFERROR(AVERAGEIFS('Cleaned Data'!$N:$N,'Cleaned Data'!$A:$A,$B11),0) -> 13.230625 | H11: =RANK(D11,$D$6:$D$35) -> 5
B12: Chrysler | C12: =SUMIFS('Cleaned Data'!$D:$D,'Cleaned Data'!$A:$A,$B12) -> 201.721 | D12: =SUMIFS('Cleaned Data'!$S:$S,'Cleaned Data'!$A:$A,$B12) -> 3461.313 | E12: =IFERROR(AVERAGEIFS('Cleaned Data'!$E:$E,'Cleaned Data'!$A:$A,$B12),0) -> 23.430833 | F12: =COUNTIFS('Cleaned Data'!$A:$A,$B12) -> 7 | G12: =IFERROR(AVERAGEIFS('Cleaned Data'!$N:$N,'Cleaned Data'!$A:$A,$B12),0) -> 14.961667 | H12: =RANK(D12,$D$6:$D$35) -> 18
B13: Dodge | C13: =SUMIFS('Cleaned Data'!$D:$D,'Cleaned Data'!$A:$A,$B13) -> 910.149 | D13: =SUMIFS('Cleaned Data'!$S:$S,'Cleaned Data'!$A:$A,$B13) -> 18000.608 | E13: =IFERROR(AVERAGEIFS('Cleaned Data'!$E:$E,'Cleaned Data'!$A:$A,$B13),0) -> 24.213636 | F13: =COUNTIFS('Cleaned Data'!$A:$A,$B13) -> 11 | G13: =IFERROR(AVERAGEIFS('Cleaned Data'!$N:$N,'Cleaned Data'!$A:$A,$B13),0) -> 16.8505 | H13: =RANK(D13,$D$6:$D$35) -> 2
B14: Ford | C14: =SUMIFS('Cleaned Data'!$D:$D,'Cleaned Data'!$A:$A,$B14) -> 2022.635 | D14: =SUMIFS('Cleaned Data'!$S:$S,'Cleaned Data'!$A:$A,$B14) -> 45776.129 | E14: =IFERROR(AVERAGEIFS('Cleaned Data'!$E:$E,'Cleaned Data'!$A:$A,$B14),0) -> 21.047273 | F14: =COUNTIFS('Cleaned Data'!$A:$A,$B14) -> 11 | G14: =IFERROR(AVERAGEIFS('Cleaned Data'!$N:$N,'Cleaned Data'!$A:$A,$B14),0) -> 12.96 | H14: =RANK(D14,$D$6:$D$35) -> 1
B15: Honda | C15: =SUMIFS('Cleaned Data'!$D:$D,'Cleaned Data'!$A:$A,$B15) -> 592.674 | D15: =SUMIFS('Cleaned Data'!$S:$S,'Cleaned Data'!$A:$A,$B15) -> 9940.3056 | E15: =IFERROR(AVERAGEIFS('Cleaned Data'!$E:$E,'Cleaned Data'!$A:$A,$B15),0) -> 20.277 | F15: =COUNTIFS('Cleaned Data'!$A:$A,$B15) -> 5 | G15: =IFERROR(AVERAGEIFS('Cleaned Data'!$N:$N,'Cleaned Data'!$A:$A,$B15),0) -> 15.557 | H15: =RANK(D15,$D$6:$D$35) -> 4
B16: Hyundai | C16: =SUMIFS('Cleaned Data'!$D:$D,'Cleaned Data'!$A:$A,$B16) -> 137.326 | D16: =SUMIFS('Cleaned Data'!$S:$S,'Cleaned Data'!$A:$A,$B16) -> 1628.0631 | E16: =IFERROR(AVERAGEIFS('Cleaned Data'!$E:$E,'Cleaned Data'!$A:$A,$B16),0) -> 12.165667 | F16: =COUNTIFS('Cleaned Data'!$A:$A,$B16) -> 3 | G16: =IFERROR(AVERAGEIFS('Cleaned Data'!$N:$N,'Cleaned Data'!$A:$A,$B16),0) -> 7.5316667 | H16: =RANK(D16,$D$6:$D$35) -> 23
B17: Infiniti | C17: =SUMIFS('Cleaned Data'!$D:$D,'Cleaned Data'!$A:$A,$B17) -> 23.713 | D17: =SUMIFS('Cleaned Data'!$S:$S,'Cleaned Data'!$A:$A,$B17) -> 698.70355 | E17: =IFERROR(AVERAGEIFS('Cleaned Data'!$E:$E,'Cleaned Data'!$A:$A,$B17),0) -> 29.465 | F17: =COUNTIFS('Cleaned Data'!$A:$A,$B17) -> 1 | G17: =IFERROR(AVERAGEIFS('Cleaned Data'!$N:$N,'Cleaned Data'!$A:$A,$B17),0) -> 19.69 | H17: =RANK(D17,$D$6:$D$35) -> 27
... B35: Volvo | C35: =SUMIFS('Cleaned Data'!$D:$D,'Cleaned Data'!$A:$A,$B35) -> 75.74 | D35: =SUMIFS('Cleaned Data'!$S:$S,'Cleaned Data'!$A:$A,$B35) -> 2249.2376 | E35: =IFERROR(AVERAGEIFS('Cleaned Data'!$E:$E,'Cleaned Data'!$A:$A,$B35),0) -> 30.933333 | F35: =COUNTIFS('Cleaned Data'!$A:$A,$B35) -> 6 | G35: =IFERROR(AVERAGEIFS('Cleaned Data'!$N:$N,'Cleaned Data'!$A:$A,$B35),0) -> 0 | H35: =RANK(D35,$D$6:$D$35) -> 19
B38: Vehicle Segment Summary
B39: Segment | C39: Total Units Sold | D39: Total Revenue ($M) | E39: Avg Price ($) | F39: Number of Models
B40: Passenger Car | C40: =SUMIFS('Cleaned Data'!$D:$D,'Cleaned Data'!$C:$C,$B40) -> 5015.184 | D40: =SUMIFS('Cleaned Data'!$S:$S,'Cleaned Data'!$C:$C,$B40) -> 101911.22 | E40: =IFERROR(AVERAGEIFS('Cleaned Data'!$E:$E,'Cleaned Data'!$C:$C,$B40),0) -> 27.7632 | F40: =COUNTIFS('Cleaned Data'!$C:$C,$B40) -> 116
B41: SUV/Truck/Van | C41: =SUMIFS('Cleaned Data'!$D:$D,'Cleaned Data'!$C:$C,$B41) -> 3305.514 | D41: =SUMIFS('Cleaned Data'!$S:$S,'Cleaned Data'!$C:$C,$B41) -> 78081.079 | E41: =IFERROR(AVERAGEIFS('Cleaned Data'!$E:$E,'Cleaned Data'!$C:$C,$B41),0) -> 26.319975 | F41: =COUNTIFS('Cleaned Data'!$C:$C,$B41) -> 41
B43: Price Tier Summary
B44: Price Tier | C44: Total Units Sold | D44: Total Revenue ($M) | E44: Avg Price ($) | F44: Number of Models
B45: Budget | C45: =SUMIFS('Cleaned Data'!$D:$D,'Cleaned Data'!$T:$T,$B45) -> 1583.203 | D45: =SUMIFS('Cleaned Data'!$S:$S,'Cleaned Data'!$T:$T,$B45) -> 19800.774 | E45: =IFERROR(AVERAGEIFS('Cleaned Data'!$E:$E,'Cleaned Data'!$T:$T,$B45),0) -> 12.692571 | F45: =COUNTIFS('Cleaned Data'!$T:$T,$B45) -> 21
B46: Mid-range | C46: =SUMIFS('Cleaned Data'!$D:$D,'Cleaned Data'!$T:$T,$B46) -> 5626.817 | D46: =SUMIFS('Cleaned Data'!$S:$S,'Cleaned Data'!$T:$T,$B46) -> 120851.33 | E46: =IFERROR(AVERAGEIFS('Cleaned Data'!$E:$E,'Cleaned Data'!$T:$T,$B46),0) -> 21.878551 | F46: =COUNTIFS('Cleaned Data'!$T:$T,$B46) -> 89
B47: Luxury | C47: =SUMIFS('Cleaned Data'!$D:$D,'Cleaned Data'!$T:$T,$B47) -> 1043.084 | D47: =SUMIFS('Cleaned Data'!$S:$S,'Cleaned Data'!$T:$T,$B47) -> 39340.19 | E47: =IFERROR(AVERAGEIFS('Cleaned Data'!$E:$E,'Cleaned Data'!$T:$T,$B47),0) -> 45.151822 | F47: =COUNTIFS('Cleaned Data'!$T:$T,$B47) -> 45
B49: Sales by Launch Year (substitute for Monthly Sales — no per-month sales data exists)
B50: Launch Year | C50: Total Units Sold | D50: Total Revenue ($M) | E50: Number of Models
B51: 2008 | C51: =SUMIFS('Cleaned Data'!$D:$D,'Cleaned Data'!$P:$P,$B51) -> 27.609 | D51: =SUMIFS('Cleaned Data'!$S:$S,'Cleaned Data'!$P:$P,$B51) -> 760.90404 | E51: =COUNTIFS('Cleaned Data'!$P:$P,$B51) -> 1
B52: 2009 | C52: =SUMIFS('Cleaned Data'!$D:$D,'Cleaned Data'!$P:$P,$B52) -> 100.635 | D52: =SUMIFS('Cleaned Data'!$S:$S,'Cleaned Data'!$P:$P,$B52) -> 1925.0126 | E52: =COUNTIFS('Cleaned Data'!$P:$P,$B52) -> 2
B53: 2011 | C53: =SUMIFS('Cleaned Data'!$D:$D,'Cleaned Data'!$P:$P,$B53) -> 3717.405 | D53: =SUMIFS('Cleaned Data'!$S:$S,'Cleaned Data'!$P:$P,$B53) -> 75978.509 | E53: =COUNTIFS('Cleaned Data'!$P:$P,$B53) -> 79
B54: 2012 | C54: =SUMIFS('Cleaned Data'!$D:$D,'Cleaned Data'!$P:$P,$B54) -> 4475.049 | D54: =SUMIFS('Cleaned Data'!$S:$S,'Cleaned Data'!$P:$P,$B54) -> 101327.87 | E54: =COUNTIFS('Cleaned Data'!$P:$P,$B54) -> 75
B56: Top 10 Best-Selling Models
B57: Rank | C57: Model | D57: Manufacturer | E57: Units Sold | F57: Revenue ($M)
B58: 1 | C58: =INDEX('Cleaned Data'!$B:$B,MATCH(LARGE('Cleaned Data'!$D$2:$D$158,1),'Cleaned Data'!$D:$D,0)) -> F-Series | D58: =INDEX('Cleaned Data'!$A:$A,MATCH(LARGE('Cleaned Data'!$D$2:$D$158,1),'Cleaned Data'!$D:$D,0)) -> Ford | E58: =LARGE('Cleaned Data'!$D$2:$D$158,1) -> 540.561 | F58: =INDEX('Cleaned Data'!$S:$S,MATCH(LARGE('Cleaned Data'!$D$2:$D$158,1),'Cleaned Data'!$D:$D,0)) -> 14560.011
B59: 2 | C59: =INDEX('Cleaned Data'!$B:$B,MATCH(LARGE('Cleaned Data'!$D$2:$D$158,2),'Cleaned Data'!$D:$D,0)) -> Explorer | D59: =INDEX('Cleaned Data'!$A:$A,MATCH(LARGE('Cleaned Data'!$D$2:$D$158,2),'Cleaned Data'!$D:$D,0)) -> Ford | E59: =LARGE('Cleaned Data'!$D$2:$D$158,2) -> 276.747 | F59: =INDEX('Cleaned Data'!$S:$S,MATCH(LARGE('Cleaned Data'!$D$2:$D$158,2),'Cleaned Data'!$D:$D,0)) -> 8836.5317
B60: 3 | C60: =INDEX('Cleaned Data'!$B:$B,MATCH(LARGE('Cleaned Data'!$D$2:$D$158,3),'Cleaned Data'!$D:$D,0)) -> Camry | D60: =INDEX('Cleaned Data'!$A:$A,MATCH(LARGE('Cleaned Data'!$D$2:$D$158,3),'Cleaned Data'!$D:$D,0)) -> Toyota | E60: =LARGE('Cleaned Data'!$D$2:$D$158,3) -> 247.994 | F60: =INDEX('Cleaned Data'!$S:$S,MATCH(LARGE('Cleaned Data'!$D$2:$D$158,3),'Cleaned Data'!$D:$D,0)) -> 4344.3589
B61: 4 | C61: =INDEX('Cleaned Data'!$B:$B,MATCH(LARGE('Cleaned Data'!$D$2:$D$158,4),'Cleaned Data'!$D:$D,0)) -> Taurus | D61: =INDEX('Cleaned Data'!$A:$A,MATCH(LARGE('Cleaned Data'!$D$2:$D$158,4),'Cleaned Data'!$D:$D,0)) -> Ford | E61: =LARGE('Cleaned Data'!$D$2:$D$158,4) -> 245.815 | F61: =INDEX('Cleaned Data'!$S:$S,MATCH(LARGE('Cleaned Data'!$D$2:$D$158,4),'Cleaned Data'!$D:$D,0)) -> 4396.4013
B62: 5 | C62: =INDEX('Cleaned Data'!$B:$B,MATCH(LARGE('Cleaned Data'!$D$2:$D$158,5),'Cleaned Data'!$D:$D,0)) -> Accord | D62: =INDEX('Cleaned Data'!$A:$A,MATCH(LARGE('Cleaned Data'!$D$2:$D$158,5),'Cleaned Data'!$D:$D,0)) -> Honda | E62: =LARGE('Cleaned Data'!$D$2:$D$158,5) -> 230.902 | F62: =INDEX('Cleaned Data'!$S:$S,MATCH(LARGE('Cleaned Data'!$D$2:$D$158,5),'Cleaned Data'!$D:$D,0)) -> 3544.3457
B63: 6 | C63: =INDEX('Cleaned Data'!$B:$B,MATCH(LARGE('Cleaned Data'!$D$2:$D$158,6),'Cleaned Data'!$D:$D,0)) -> Ram Pickup | D63: =INDEX('Cleaned Data'!$A:$A,MATCH(LARGE('Cleaned Data'!$D$2:$D$158,6),'Cleaned Data'!$D:$D,0)) -> Dodge | E63: =LARGE('Cleaned Data'!$D$2:$D$158,6) -> 227.061 | F63: =INDEX('Cleaned Data'!$S:$S,MATCH(LARGE('Cleaned Data'!$D$2:$D$158,6),'Cleaned Data'!$D:$D,0)) -> 4418.6071
B64: 7 | C64: =INDEX('Cleaned Data'!$B:$B,MATCH(LARGE('Cleaned Data'!$D$2:$D$158,7),'Cleaned Data'!$D:$D,0)) -> Ranger | D64: =INDEX('Cleaned Data'!$A:$A,MATCH(LARGE('Cleaned Data'!$D$2:$D$158,7),'Cleaned Data'!$D:$D,0)) -> Ford | E64: =LARGE('Cleaned Data'!$D$2:$D$158,7) -> 220.65 | F64: =INDEX('Cleaned Data'!$S:$S,MATCH(LARGE('Cleaned Data'!$D$2:$D$158,7),'Cleaned Data'!$D:$D,0)) -> 2658.8325
B65: 8 | C65: =INDEX('Cleaned Data'!$B:$B,MATCH(LARGE('Cleaned Data'!$D$2:$D$158,8),'Cleaned Data'!$D:$D,0)) -> Civic | D65: =INDEX('Cleaned Data'!$A:$A,MATCH(LARGE('Cleaned Data'!$D$2:$D$158,8),'Cleaned Data'!$D:$D,0)) -> Honda | E65: =LARGE('Cleaned Data'!$D$2:$D$158,8) -> 199.685 | F65: =INDEX('Cleaned Data'!$S:$S,MATCH(LARGE('Cleaned Data'!$D$2:$D$158,8),'Cleaned Data'!$D:$D,0)) -> 2572.9412
B66: 9 | C66: =INDEX('Cleaned Data'!$B:$B,MATCH(LARGE('Cleaned Data'!$D$2:$D$158,9),'Cleaned Data'!$D:$D,0)) -> Caravan | D66: =INDEX('Cleaned Data'!$A:$A,MATCH(LARGE('Cleaned Data'!$D$2:$D$158,9),'Cleaned Data'!$D:$D,0)) -> Dodge | E66: =LARGE('Cleaned Data'!$D$2:$D$158,9) -> 181.749 | F66: =INDEX('Cleaned Data'!$S:$S,MATCH(LARGE('Cleaned Data'!$D$2:$D$158,9),'Cleaned Data'!$D:$D,0)) -> 3555.9192
B67: 10 | C67: =INDEX('Cleaned Data'!$B:$B,MATCH(LARGE('Cleaned Data'!$D$2:$D$158,10),'Cleaned Data'!$D:$D,0)) -> Focus | D67: =INDEX('Cleaned Data'!$A:$A,MATCH(LARGE('Cleaned Data'!$D$2:$D$158,10),'Cleaned Data'!$D:$D,0)) -> Ford | E67: =LARGE('Cleaned Data'!$D$2:$D$158,10) -> 175.67 | F67: =INDEX('Cleaned Data'!$S:$S,MATCH(LARGE('Cleaned Data'!$D$2:$D$158,10),'Cleaned Data'!$D:$D,0)) -> 2163.376

Sheet Lookup
BI1: Acura | BJ1: {=_xlfn.UNIQUE(BI1:BI157)} -> Acura
B2: Model Lookup Tool | BI2: Acura | BJ2: Audi
BI3: Acura | BJ3: BMW
BI4: Acura | BJ4: Buick
B5: Search Model: | C5: GTI | BI5: Audi | BJ5: Cadillac
BI6: Audi | BJ6: Chevrolet
B7: Manufacturer | C7: =IFERROR(INDEX('Cleaned Data'!A:A,MATCH($C$5,'Cleaned Data'!B:B,0)),"Model not found") -> Volkswagen | BI7: Audi | BJ7: Chrysler
B8: Price, $ (VLOOKUP) | C8: =IFERROR(VLOOKUP($C$5,'Cleaned Data'!B:E,4,FALSE()),"Model not found") -> 17.5 | BI8: BMW | BJ8: Dodge
B9: Units Sold | C9: =IFERROR(INDEX('Cleaned Data'!D:D,MATCH($C$5,'Cleaned Data'!B:B,0)),"Model not found") -> 5.596 | BI9: BMW | BJ9: Ford
B10: Revenue, $M | C10: =IFERROR(INDEX('Cleaned Data'!S:S,MATCH($C$5,'Cleaned Data'!B:B,0)),"Model not found") -> 97.93 | BI10: BMW | BJ10: Honda
B11: Vehicle Segment | C11: =IFERROR(INDEX('Cleaned Data'!C:C,MATCH($C$5,'Cleaned Data'!B:B,0)),"Model not found") -> Passenger Car | BI11: Buick | BJ11: Hyundai
B12: Price Tier | C12: =IFERROR(INDEX('Cleaned Data'!T:T,MATCH($C$5,'Cleaned Data'!B:B,0)),"Model not found") -> Mid-range | BI12: Buick | BJ12: Infiniti
B13: Sales Rank (1 = highest) | C13: =IFERROR(INDEX('Cleaned Data'!V:V,MATCH($C$5,'Cleaned Data'!B:B,0)),"Model not found") -> 141 | BI13: Buick | BJ13: Jaguar
B14: Launch Date | C14: =IFERROR(INDEX('Cleaned Data'!O:O,MATCH($C$5,'Cleaned Data'!B:B,0)),"Model not found") -> 40634 | BI14: Buick | BJ14: Jeep
BI15: Cadillac | BJ15: Lexus
BI16: Cadillac | BJ16: Lincoln
B17: Brand Lookup (VLOOKUP against Analysis!Brand Summary) | BI17: Cadillac | BJ17: Mitsubishi
B18: Search Brand: | C18: Chevrolet | BI18: Cadillac | BJ18: Mercury
B19: Total Units Sold | C19: =IFERROR(VLOOKUP($C$18,Analysis!$B$5:$H$36,2,FALSE()),"Brand not found") -> 554.365 | BI19: Cadillac | BJ19: Mercedes-Benz
B20: Total Revenue, $ | C20: =IFERROR(VLOOKUP($C$18,Analysis!$B$5:$H$36,3,FALSE()),"Brand not found") -> 9610.6533 | BI20: Chevrolet | BJ20: Nissan
B21: Average Price, $ | C21: =IFERROR(VLOOKUP($C$18,Analysis!$B$5:$H$36,4,FALSE()),"Brand not found") -> 20.022778 | BI21: Chevrolet | BJ21: Oldsmobile
B22: Number of Models | C22: =IFERROR(VLOOKUP($C$18,Analysis!$B$5:$H$36,5,FALSE()),"Brand not found") -> 9 | BI22: Chevrolet | BJ22: Plymouth
B23: Revenue Rank | C23: =IFERROR(VLOOKUP($C$18,Analysis!$B$5:$H$36,7,FALSE()),"Brand not found") -> 5 | BI23: Chevrolet | BJ23: Pontiac
BI24: Chevrolet | BJ24: Porsche
BI25: Chevrolet | BJ25: Saab
BI26: Chevrolet | BJ26: Saturn
BI27: Chevrolet | BJ27: Subaru
BI28: Chevrolet | BJ28: Toyota
BI29: Chrysler | BJ29: Volkswagen
BI30: Chrysler | BJ30: Volvo
BI31: Chrysler
BI32: Chrysler
BI33: Chrysler
BI34: Chrysler
BI35: Chrysler
BI36: Dodge
BI37: Dodge
BI38: Dodge
BI39: Dodge
BI40: Dodge
BI41: Dodge
BI42: Dodge
... BI157: Volvo

Sheet Business Answers
B2: Business Questions — Answered Live with Formulas
B4: Which car brand generates the highest revenue?
B5: =INDEX(Analysis!$B$6:$B$35,MATCH(MAX(Analysis!$D$6:$D$35),Analysis!$D$6:$D$35,0))&" ($"&TEXT(MAX(Analysis!$D$6:$D$35),"#,##0.0")&"M)" -> Ford ($45,776.1M)
B7: Which model sells the most?
B8: =Analysis!C58&" ("&TEXT(Analysis!E58,"#,##0.0")&"k units)" -> F-Series (540.6k units)
B10: Which launch year has the highest total sales? (proxy for "highest month" — no monthly data exists)
B11: =INDEX(Analysis!$B$51:$B$54,MATCH(MAX(Analysis!$C$51:$C$54),Analysis!$C$51:$C$54,0)) -> 2012
B13: What is the average selling price across all models?
B14: ="$"&TEXT(AVERAGE('Cleaned Data'!$E$2:$E$158),"#,##0.0")&"k" -> $27.4k
B16: Which brands have the highest average price?
B17: =INDEX(Analysis!$B$6:$B$35,MATCH(MAX(Analysis!$E$6:$E$35),Analysis!$E$6:$E$35,0))&" (avg $"&TEXT(MAX(Analysis!$E$6:$E$35),"#,##0.0")&"k)" -> Porsche (avg $62.5k)
B19: Are expensive cars selling less than cheaper cars?
B20: =IF(CORREL('Cleaned Data'!$E$2:$E$158,'Cleaned Data'!$D$2:$D$158)<0,"Yes — price and units sold are negatively correlated (correlation: "&TEXT(CORREL('Cleaned Data'!$E$2:$E$158,'Cleaned Data'!$D$2:$D$158),"0.00")&"). See the Price vs Units Sold scatter chart.","No clear negative relationship (correlation: "&TEXT(CORREL('Cleaned Data'!$E$2:$E$158,'Cleaned Data'!$D$2:$D$158),"0.00")&").") -> Yes — price and units sold are negatively correlated (correlation: -0.30). See the Price vs Units Sold scatter chart.
